{
    "，": 0,
    "的": 1,
    "我": 2,
    "了": 3,
    "。": 4,
    "：": 5,
    "说": 6,
    "是": 7,
    "你": 8,
    "就": 9,
    "在": 10,
    "！": 11,
    "事": 12,
    "他": 13,
    "糗": 14,
    "…": 15,
    "？": 16,
    "都": 17,
    "“": 18,
    "她": 19,
    "”": 20,
    "不": 21,
    "着": 22,
    "去": 23,
    "一个": 24,
    "也": 25,
    "给": 26,
    "把": 27,
    "有": 28,
    ":": 29,
    "看": 30,
    "没": 31,
    "到": 32,
    "还": 33,
    "要": 34,
    "和": 35,
    "这": 36,
    "上": 37,
    "吃": 38,
    "又": 39,
    "问": 40,
    "儿子": 41,
    "那": 42,
    "时候": 43,
    "人": 44,
    "啊": 45,
    "一": 46,
    "来": 47,
    "想": 48,
    "对": 49,
    "媳妇": 50,
    "买": 51,
    "里": 52,
    "好": 53,
    "跟": 54,
    "什么": 55,
    "吗": 56,
    "我们": 57,
    "今天": 58,
    "走": 59,
    "后": 60,
    "个": 61,
    "孩子": 62,
    "被": 63,
    "吧": 64,
    "没有": 65,
    "小": 66,
    "跑": 67,
    "让": 68,
    "然后": 69,
    "还是": 70,
    "知道": 71,
    "找": 72,
    "自己": 73,
    "时": 74,
    "会": 75,
    "怎么": 76,
    "回家": 77,
    "做": 78,
    "等": 79,
    "就是": 80,
    "很": 81,
    "打": 82,
    "用": 83,
    "老公": 84,
    "过": 85,
    "能": 86,
    "拿": 87,
    "小叔": 88,
    "老婆": 89,
    "呢": 90,
    "钱": 91,
    "现在": 92,
    "大": 93,
    "看到": 94,
    "家里": 95,
    "啥": 96,
    "发现": 97,
    "女儿": 98,
    "公司": 99,
    "突然": 100,
    "他们": 101,
    "这个": 102,
    "叫": 103,
    "多": 104,
    "不是": 105,
    "可": 106,
    "老妈": 107,
    "带": 108,
    "挺": 109,
    "妈": 110,
    "听": 111,
    "手机": 112,
    "出来": 113,
    "闺蜜": 114,
    "看着": 115,
    "一起": 116,
    "地": 117,
    "觉得": 118,
    "老师": 119,
    "再": 120,
    "玩": 121,
    "看见": 122,
    "这么": 123,
    "一下": 124,
    "谁": 125,
    "才": 126,
    "喜欢": 127,
    "哭": 128,
    "晚上": 129,
    "老爸": 130,
    "不能": 131,
    "同事": 132,
    "从": 133,
    "道": 134,
    "过去": 135,
    "感觉": 136,
    "于是": 137,
    "妈妈": 138,
    "家": 139,
    "不要": 140,
    "过年": 141,
    "一直": 142,
    "]": 143,
    "你们": 144,
    "几个": 145,
    "衣服": 146,
    "点": 147,
    "起来": 148,
    "工作": 149,
    "朋友": 150,
    "还有": 151,
    "告诉": 152,
    "得": 153,
    "、": 154,
    "回来": 155,
    "准备": 156,
    "完": 157,
    "后来": 158,
    "昨天": 159,
    "大妈": 160,
    "下": 161,
    "[": 162,
    "说道": 163,
    "睡": 164,
    "这样": 165,
    "因为": 166,
    "开始": 167,
    "小时候": 168,
    "过来": 169,
    "大哥": 170,
    "同学": 171,
    "最后": 172,
    "吃饭": 173,
    "换": 174,
    "大家": 175,
    "爸": 176,
    "我爸": 177,
    "不敢": 178,
    "—": 179,
    "那天": 180,
    "帮": 181,
    "孃": 182,
    "一只": 183,
    "快": 184,
    "可以": 185,
    "正": 186,
    "穿": 187,
    "刚刚": 188,
    "送": 189,
    "老板": 190,
    "吓": 191,
    "我家": 192,
    "爸妈": 193,
    "打电话": 194,
    "我妈": 195,
    "毕业": 196,
    "结果": 197,
    "直接": 198,
    "当": 199,
    "美女": 200,
    "一点": 201,
    "东西": 202,
    "一定": 203,
    "一顿": 204,
    "早上": 205,
    "班花": 206,
    "盛": 207,
    "狐小乔": 208,
    "哥哥": 209,
    "那么": 210,
    "坐在": 211,
    "见": 212,
    "五": 213,
    "只": 214,
    "居然": 215,
    "坐": 216,
    "那个": 217,
    "一句": 218,
    "班主任": 219,
    "电话": 220,
    "可是": 221,
    "有个": 222,
    "想着": 223,
    "两个": 224,
    "抱": 225,
    "以后": 226,
    "当时": 227,
    "新": 228,
    "门口": 229,
    "女": 230,
    "猫": 231,
    "大人": 232,
    "真的": 233,
    "们": 234,
    ".": 235,
    "不到": 236,
    "为了": 237,
    "怕": 238,
    "回": 239,
    "两碗": 240,
    "下班": 241,
    "以前": 242,
    "但": 243,
    "竟然": 244,
    "有点": 245,
    "一天": 246,
    "结婚": 247,
    "心里": 248,
    "刚": 249,
    "路上": 250,
    "出": 251,
    "所以": 252,
    "真": 253,
    "可能": 254,
    "​": 255,
    "师傅": 256,
    "揍": 257,
    "看看": 258,
    "狗": 259,
    "每次": 260,
    "洗": 261,
    "笑": 262,
    "最": 263,
    "眼睛": 264,
    "地方": 265,
    "死": 266,
    "呀": 267,
    "是不是": 268,
    "旁边": 269,
    "第二天": 270,
    "比": 271,
    "已经": 272,
    "电影": 273,
    "领导": 274,
    "一边": 275,
    "前": 276,
    "不会": 277,
    "出差": 278,
    "介绍": 279,
    "别人": 280,
    "月": 281,
    "像": 282,
    "终于": 283,
    "放": 284,
    "时间": 285,
    "里面": 286,
    "赶紧": 287,
    "它": 288,
    "往": 289,
    "人家": 290,
    "几天": 291,
    "漂亮": 292,
    "侄子": 293,
    "话": 294,
    "（": 295,
    "说话": 296,
    "扔": 297,
    "不好": 298,
    "后面": 299,
    "最近": 300,
    "却": 301,
    "长大": 302,
    "表哥": 303,
    "）": 304,
    "的话": 305,
    "女同学": 306,
    "喝": 307,
    "黄瓜": 308,
    "饭": 309,
    "前面": 310,
    "边": 311,
    "只有": 312,
    "站": 313,
    "咋": 314,
    "砸": 315,
    "忍不住": 316,
    "学校": 317,
    "与": 318,
    "爸爸": 319,
    "睡觉": 320,
    "啦": 321,
    "捡": 322,
    "很多": 323,
    "妹子": 324,
    "拍": 325,
    "掉": 326,
    "胖": 327,
    "养": 328,
    "一次": 329,
    "老家": 330,
    "您": 331,
    "头发": 332,
    "为": 333,
    "女友": 334,
    "鞋子": 335,
    "平时": 336,
    "喊": 337,
    "高": 338,
    "累": 339,
    "不了": 340,
    "发": 341,
    "...": 342,
    "上班": 343,
    "一家": 344,
    "办公室": 345,
    "开车": 346,
    "声音": 347,
    "进": 348,
    "嫂子": 349,
    "中": 350,
    "二哈": 351,
    "～": 352,
    "经常": 353,
    "偷偷": 354,
    "原来": 355,
    "正在": 356,
    "夏天": 357,
    "收拾": 358,
    "起床": 359,
    "一眼": 360,
    "群里": 361,
    "如果": 362,
    "老": 363,
    "而": 364,
    "书包": 365,
    "不过": 366,
    "面试": 367,
    "并": 368,
    "一些": 369,
    "开": 370,
    "卖": 371,
    "听见": 372,
    "放学": 373,
    "决定": 374,
    "老板娘": 375,
    "司机": 376,
    "男友": 377,
    "骑着": 378,
    "写": 379,
    "女人": 380,
    "接": 381,
    "太": 382,
    "打开": 383,
    "中国": 384,
    "在家": 385,
    "骂": 386,
    "加油": 387,
    "小孩": 388,
    "居士": 389,
    "身边": 390,
    "身上": 391,
    "表妹": 392,
    "一样": 393,
    "一把": 394,
    "人生": 395,
    "这时": 396,
    "总": 397,
    "逛街": 398,
    "接着": 399,
    "有没有": 400,
    "外甥": 401,
    "......": 402,
    "?": 403,
    "说完": 404,
    "样子": 405,
    "厕所": 406,
    "脸": 407,
    "一声": 408,
    "生": 409,
    "住": 410,
    "男": 411,
    "胖丫": 412,
    "实在": 413,
    "下来": 414,
    "女朋友": 415,
    "尴尬": 416,
    "这里": 417,
    "抢": 418,
    "不行": 419,
    "日本": 420,
    "一片": 421,
    "硬币": 422,
    "书": 423,
    "一脸": 424,
    "找到": 425,
    "女孩": 426,
    "脑袋": 427,
    "两天": 428,
    "连": 429,
    "比较": 430,
    "进来": 431,
    "啃": 432,
    "咬": 433,
    "腿": 434,
    "愣": 435,
    "三个": 436,
    "花开": 437,
    "二零二一": 438,
    "起": 439,
    "变成": 440,
    "表弟": 441,
    "有人": 442,
    "一条": 443,
    "小学": 444,
    "阿姨": 445,
    "关系": 446,
    "小时": 447,
    "各种": 448,
    "半天": 449,
    "躲": 450,
    "男人": 451,
    "么": 452,
    "中年人": 453,
    "听说": 454,
    "经理": 455,
    "立马": 456,
    "一年": 457,
    "小姨子": 458,
    "头": 459,
    "那时": 460,
    "衣柜": 461,
    "继续": 462,
    "劝": 463,
    "跳": 464,
    "外卖": 465,
    "袋子": 466,
    "‘": 467,
    "踩": 468,
    "发生": 469,
    "饺子": 470,
    "脸上": 471,
    "以为": 472,
    "今年": 473,
    "老大爷": 474,
    "第一次": 475,
    "洗车": 476,
    "陪": 477,
    "红包": 478,
    "父母": 479,
    "男朋友": 480,
    "甚至": 481,
    "水": 482,
    "更": 483,
    "明天": 484,
    "其中": 485,
    "无心": 486,
    "哪里": 487,
    "胸": 488,
    "踢": 489,
    "一脚": 490,
    "大学": 491,
    "车上": 492,
    "而且": 493,
    "急": 494,
    "特意": 495,
    "总是": 496,
    "抓": 497,
    "下午": 498,
    "抓住": 499,
    "手": 500,
    "不够": 501,
    "谈": 502,
    "泡": 503,
    "生意": 504,
    "干": 505,
    "班": 506,
    "想到": 507,
    "咯咯": 508,
    "天天": 509,
    "车子": 510,
    "嫌": 511,
    "丑": 512,
    "肉": 513,
    "外面": 514,
    "马上": 515,
    "东北": 516,
    "俩": 517,
    "请": 518,
    "顿时": 519,
    "直到": 520,
    "多年": 521,
    "该": 522,
    "咯": 523,
    "车": 524,
    "回到": 525,
    "堂妹": 526,
    "顺便": 527,
    "几年": 528,
    "爷爷": 529,
    "妹妹": 530,
    "似的": 531,
    "五叔": 532,
    "早点": 533,
    "倒": 534,
    "成功": 535,
    "回去": 536,
    "哦": 537,
    "哎": 538,
    "皮带": 539,
    "好看": 540,
    "真是": 541,
    "床上": 542,
    "打断": 543,
    "出去": 544,
    "楼下": 545,
    "中午": 546,
    "提前": 547,
    "对象": 548,
    "安排": 549,
    "机器人": 550,
    "路过": 551,
    "叔叔": 552,
    "身材": 553,
    "需要": 554,
    "窗户": 555,
    "刚才": 556,
    "记得": 557,
    "擦": 558,
    "网吧": 559,
    "讲": 560,
    "羊": 561,
    "女生": 562,
    "初中": 563,
    "聊天": 564,
    "菜": 565,
    "真主": 566,
    "原因": 567,
    "闺女": 568,
    "’": 569,
    "日子": 570,
    "一件": 571,
    "遇到": 572,
    "身体": 573,
    "帮忙": 574,
    "特别": 575,
    "离婚": 576,
    "只是": 577,
    "岳父": 578,
    "上面": 579,
    "服务员": 580,
    "厨房": 581,
    "沙发": 582,
    "已": 583,
    "信息": 584,
    "外甥女": 585,
    "放在": 586,
    "阿": 587,
    "哒": 588,
    "刚好": 589,
    "A": 590,
    "刷": 591,
    "必须": 592,
    "动物": 593,
    "尿裤子": 594,
    "瞅": 595,
    "白": 596,
    "挂": 597,
    "创可贴": 598,
    "慢": 599,
    "相亲": 600,
    "作业": 601,
    "忧郁": 602,
    "长": 603,
    "天": 604,
    "洗澡": 605,
    "同意": 606,
    "想起": 607,
    "楼": 608,
    "向": 609,
    "裤子": 610,
    "患者": 611,
    "心中": 612,
    "偷": 613,
    "烟": 614,
    "小子": 615,
    "临近": 616,
    "挖": 617,
    "鼻孔": 618,
    "她们": 619,
    "无聊": 620,
    "肩膀": 621,
    "行": 622,
    "牛": 623,
    "小姐姐": 624,
    "蛋": 625,
    "打游戏": 626,
    "反正": 627,
    "问题": 628,
    "电视": 629,
    "招聘": 630,
    "为啥": 631,
    "别": 632,
    "本来": 633,
    "要是": 634,
    "奶奶": 635,
    "应该": 636,
    "躺": 637,
    "认识": 638,
    "狠狠": 639,
    "随": 640,
    "一块": 641,
    "字": 642,
    "答应": 643,
    "五岁": 644,
    "门": 645,
    "一旁": 646,
    "父亲": 647,
    "这是": 648,
    "小伙子": 649,
    "一般": 650,
    "发来": 651,
    "一双": 652,
    "室友": 653,
    "下面": 654,
    "情况": 655,
    "噗": 656,
    "身高": 657,
    "出门": 658,
    "那种": 659,
    "从此": 660,
    "桌子": 661,
    "大姐": 662,
    "检查": 663,
    "随着": 664,
    "事情": 665,
    "嘴": 666,
    "塑料袋": 667,
    "其实": 668,
    "高兴": 669,
    "不想": 670,
    "长得": 671,
    "多少": 672,
    "考试": 673,
    "北极": 674,
    "发小": 675,
    "工作人员": 676,
    "周": 677,
    "主任": 678,
    "小女孩": 679,
    "本人": 680,
    "复习": 681,
    "丢": 682,
    "房子": 683,
    "有次": 684,
    "干活": 685,
    "听到": 686,
    "好多": 687,
    "十年": 688,
    "她家": 689,
    "教育": 690,
    "半年": 691,
    "姑娘": 692,
    ")": 693,
    "一枚": 694,
    "成为": 695,
    "天热": 696,
    "邻居": 697,
    "坏": 698,
    "上学": 699,
    "嗓子": 700,
    "我哥": 701,
    "--": 702,
    "球": 703,
    "果然": 704,
    "单位": 705,
    "去年": 706,
    "一瓶": 707,
    "放假": 708,
    "好像": 709,
    "忙": 710,
    "最终": 711,
    "信": 712,
    "元": 713,
    "瞬间": 714,
    "去世": 715,
    "看中": 716,
    "要求": 717,
    "每天": 718,
    "没事": 719,
    "减肥": 720,
    "奶": 721,
    "药": 722,
    "针": 723,
    "打鼓": 724,
    "屁": 725,
    "刘": 726,
    "修理": 727,
    "先": 728,
    "见面": 729,
    "做饭": 730,
    "默默": 731,
    "母亲": 732,
    "一口": 733,
    "口袋": 734,
    "2": 735,
    "家长": 736,
    "他家": 737,
    "对方": 738,
    "内功": 739,
    "看不上": 740,
    "请问": 741,
    "小号": 742,
    "昨晚": 743,
    "疼": 744,
    "抱怨": 745,
    "秘密": 746,
    "°": 747,
    "家门口": 748,
    "名字": 749,
    "一会": 750,
    "转身": 751,
    "前段时间": 752,
    "这种": 753,
    "就要": 754,
    "照片": 755,
    "一次性": 756,
    "留": 757,
    "撞死": 758,
    "望": 759,
    "一看": 760,
    "那年": 761,
    "世界": 762,
    "除了": 763,
    "休息": 764,
    "蚊子": 765,
    "南方": 766,
    "表妹夫": 767,
    "幼儿园": 768,
    "爱上": 769,
    "钓鱼": 770,
    "老爹": 771,
    "研究": 772,
    "车间": 773,
    "前男友": 774,
    "完成": 775,
    "感冒": 776,
    "非常": 777,
    "忘": 778,
    "着急": 779,
    "剪": 780,
    "踹": 781,
    "满意": 782,
    "几次": 783,
    "愿意": 784,
    "爱": 785,
    "第一": 786,
    "两岁": 787,
    "黑": 788,
    "驾照": 789,
    "医生": 790,
    "每个": 791,
    "难道": 792,
    "扎": 793,
    "咱们": 794,
    "奇迹": 795,
    "干嘛": 796,
    "白酒": 797,
    "买点": 798,
    "好消息": 799,
    "医院": 800,
    "女子": 801,
    "栗子": 802,
    "通知": 803,
    "心疼": 804,
    "反应": 805,
    "工具": 806,
    "转过": 807,
    "米饭": 808,
    "娃": 809,
    "脚": 810,
    "依然": 811,
    "安全": 812,
    "sir": 813,
    "中间": 814,
    "四个": 815,
    "你家": 816,
    "一款": 817,
    "意思": 818,
    "摘": 819,
    "动作": 820,
    "果断": 821,
    "不错": 822,
    "能力": 823,
    "外地": 824,
    "饭店": 825,
    "回复": 826,
    "到处": 827,
    "接受": 828,
    "大夫": 829,
    "当初": 830,
    "一年级": 831,
    "一会儿": 832,
    "洗碗": 833,
    "路": 834,
    "加班": 835,
    "打呼噜": 836,
    "取": 837,
    "卡": 838,
    "接过": 839,
    "一位": 840,
    "还要": 841,
    "生气": 842,
    "激动": 843,
    "子": 844,
    "阳台": 845,
    "哪": 846,
    "面前": 847,
    "两": 848,
    "对面": 849,
    "好久": 850,
    "通宵": 851,
    "王八": 852,
    "吃瓜": 853,
    "打扮": 854,
    "好奇": 855,
    "考虑": 856,
    "差点": 857,
    "当然": 858,
    "努力": 859,
    "小伙伴": 860,
    "好吃": 861,
    "眼泪": 862,
    "可爱": 863,
    "小孩子": 864,
    "圣诞": 865,
    "另": 866,
    "圣诞节": 867,
    "面": 868,
    "上个月": 869,
    "红色": 870,
    "女同事": 871,
    "~": 872,
    "包": 873,
    "旧梦": 874,
    "伞": 875,
    "年": 876,
    "船长": 877,
    "女神": 878,
    "嘞": 879,
    "安慰": 880,
    "块": 881,
    "堵": 882,
    "鼻涕": 883,
    "剩": 884,
    "最好": 885,
    "收": 886,
    "胡子": 887,
    "定": 888,
    "胳膊": 889,
    "商量": 890,
    "问道": 891,
    "吭声": 892,
    "帽": 893,
    "璃": 894,
    "为什么": 895,
    "解释": 896,
    "石锅": 897,
    "地瓜": 898,
    "狐": 899,
    "心想": 900,
    "嘛": 901,
    "半夜": 902,
    "春节": 903,
    "那些": 904,
    "黑大": 905,
    "理发店": 906,
    "醒": 907,
    "所有": 908,
    "秋": 909,
    "餐具": 910,
    "奖励": 911,
    "排": 912,
    "黑色": 913,
    "期间": 914,
    "包子": 915,
    "朋友圈": 916,
    "那样": 917,
    "大米": 918,
    "第三天": 919,
    "打脸": 920,
    "半个": 921,
    "跟着": 922,
    "考": 923,
    "100": 924,
    "飞": 925,
    "空城": 926,
    "肯定": 927,
    "莫名其妙": 928,
    "电视剧": 929,
    "还好": 930,
    "武术": 931,
    "一张": 932,
    "犹豫": 933,
    "一阵": 934,
    "我俩": 935,
    "当场": 936,
    "被窝": 937,
    "早": 938,
    "调皮捣蛋": 939,
    "成": 940,
    "阿雷": 941,
    "嗯": 942,
    "男孩": 943,
    "跨": 944,
    "冲": 945,
    "递": 946,
    "做客": 947,
    "母鸡": 948,
    "打个": 949,
    "宿舍": 950,
    "还会": 951,
    "啫喱": 952,
    "担心": 953,
    "谁知": 954,
    "再说": 955,
    "儿": 956,
    "有些": 957,
    "不用": 958,
    "接到": 959,
    "记忆": 960,
    "不止": 961,
    "感慨": 962,
    "吵": 963,
    "扫地": 964,
    "一场": 965,
    "盯": 966,
    "小朋友": 967,
    "很大": 968,
    "抽": 969,
    "糖": 970,
    "两口子": 971,
    "美人": 972,
    "显得": 973,
    "商场": 974,
    "拌": 975,
    "怀疑": 976,
    "二手": 977,
    "管": 978,
    "程": 979,
    "进去": 980,
    "任务": 981,
    "很早以前": 982,
    "做好": 983,
    "铁棍": 984,
    "参加": 985,
    "前途": 986,
    "碰": 987,
    "学": 988,
    "早餐": 989,
    "马路": 990,
    "纸": 991,
    "某位": 992,
    "理由": 993,
    "今晚": 994,
    "拖": 995,
    "搓澡": 996,
    "村民": 997,
    "天下": 998,
    "拉": 999,
    "俺": 1000,
    "追": 1001,
    "放到": 1002,
    "包装": 1003,
    "上门": 1004,
    "钻": 1005,
    "往里面": 1006,
    "B": 1007,
    "客厅": 1008,
    "由": 1009,
    "百": 1010,
    "花": 1011,
    "鸡": 1012,
    "年轻": 1013,
    "之前": 1014,
    "谢谢": 1015,
    "本地": 1016,
    "憋": 1017,
    "工厂": 1018,
    "吃过饭": 1019,
    "印象": 1020,
    "床单": 1021,
    "呆": 1022,
    "英语": 1023,
    "干脆": 1024,
    "堂哥": 1025,
    "背": 1026,
    "一听": 1027,
    "不许": 1028,
    "仙女": 1029,
    "娘家": 1030,
    "弄": 1031,
    "三年": 1032,
    "蕾丝": 1033,
    "视频": 1034,
    "景区": 1035,
    "杀": 1036,
    "南九": 1037,
    "怀孕": 1038,
    "不对劲": 1039,
    "小狗": 1040,
    "鼻子": 1041,
    "口罩": 1042,
    "呗": 1043,
    "属": 1044,
    "发到": 1045,
    "留下": 1046,
    "其他": 1047,
    "精神": 1048,
    "食堂": 1049,
    "点头": 1050,
    "目光": 1051,
    "摇头": 1052,
    "经络": 1053,
    "补": 1054,
    "酒": 1055,
    "被子": 1056,
    "上课": 1057,
    "忽悠": 1058,
    "提": 1059,
    "无果": 1060,
    "块钱": 1061,
    "想要": 1062,
    "瞪": 1063,
    "规矩": 1064,
    "只能": 1065,
    "租": 1066,
    "嘿嘿": 1067,
    "单身": 1068,
    "隔壁": 1069,
    "这件": 1070,
    "来到": 1071,
    "电": 1072,
    "学生": 1073,
    "小强": 1074,
    "好玩": 1075,
    "窗外": 1076,
    "藏": 1077,
    "这次": 1078,
    "结束": 1079,
    "这些": 1080,
    "吃晚饭": 1081,
    "眼看": 1082,
    "傻子": 1083,
    "好不容易": 1084,
    "蓝色": 1085,
    "文员": 1086,
    "换个": 1087,
    "开心": 1088,
    "一共": 1089,
    "社区": 1090,
    "但是": 1091,
    "票": 1092,
    "剩下": 1093,
    "一辆": 1094,
    "挡": 1095,
    "放心": 1096,
    "大姨": 1097,
    "情人节": 1098,
    "压岁钱": 1099,
    "拿出": 1100,
    "只见": 1101,
    "数据线": 1102,
    "玩游戏": 1103,
    "丈母娘": 1104,
    "澡盆": 1105,
    "懂": 1106,
    "前两天": 1107,
    "双鞋": 1108,
    "荷叶": 1109,
    "三": 1110,
    "心": 1111,
    "小声": 1112,
    "追溯": 1113,
    "时代": 1114,
    "打拼": 1115,
    "东京": 1116,
    "出现": 1117,
    "李": 1118,
    "线下": 1119,
    "烧鸡": 1120,
    "*": 1121,
    "鞋": 1122,
    "估计": 1123,
    "掏出": 1124,
    "汗": 1125,
    "难受": 1126,
    "整个": 1127,
    "一身": 1128,
    "于": 1129,
    "冰棒": 1130,
    "祖传": 1131,
    "上车": 1132,
    "九": 1133,
    "便": 1134,
    "便宜": 1135,
    "没想到": 1136,
    "本": 1137,
    "场": 1138,
    "教室": 1139,
    "中学": 1140,
    "街上": 1141,
    "扭头": 1142,
    "次": 1143,
    "腰": 1144,
    "核酸": 1145,
    "祖母": 1146,
    "86": 1147,
    "收银": 1148,
    "上司": 1149,
    "一科": 1150,
    "不再": 1151,
    "属于": 1152,
    "近视": 1153,
    "村里": 1154,
    "天气": 1155,
    "检测": 1156,
    "老太太": 1157,
    "一杯": 1158,
    "转": 1159,
    "意识": 1160,
    "石科": 1161,
    "工地": 1162,
    "下去": 1163,
    "男生": 1164,
    "达到": 1165,
    "那里": 1166,
    "不知": 1167,
    "聊": 1168,
    "退休": 1169,
    "鱼": 1170,
    "哥们": 1171,
    "伤": 1172,
    "安检": 1173,
    "不管": 1174,
    "了解": 1175,
    "老总": 1176,
    "一排": 1177,
    "超市": 1178,
    "甩": 1179,
    "失恋": 1180,
    "碗": 1181,
    "地上": 1182,
    "浴缸": 1183,
    "手里": 1184,
    "毛病": 1185,
    "正式": 1186,
    "喝完": 1187,
    "指着": 1188,
    "姥姥家": 1189,
    "呦": 1190,
    "惊讶": 1191,
    "反而": 1192,
    "哥": 1193,
    "喂": 1194,
    "老头": 1195,
    "收到": 1196,
    "刮": 1197,
    "凉风": 1198,
    "以": 1199,
    "贵": 1200,
    "骑": 1201,
    "看书": 1202,
    "高僧": 1203,
    "干净": 1204,
    "弟子": 1205,
    "那一刻": 1206,
    "负责": 1207,
    "二十多年": 1208,
    "礼貌": 1209,
    "懵": 1210,
    "确定": 1211,
    "据": 1212,
    "一批": 1213,
    "房间": 1214,
    "感人": 1215,
    "确实": 1216,
    "屋里": 1217,
    "沟": 1218,
    "幸好": 1219,
    "二代": 1220,
    "大声": 1221,
    "尿": 1222,
    "大四": 1223,
    "咬伤": 1224,
    "好心": 1225,
    "高铁": 1226,
    "北京": 1227,
    "战力": 1228,
    "再次": 1229,
    "望月": 1230,
    "微创": 1231,
    "最高": 1232,
    "展开": 1233,
    "插上": 1234,
    "婚礼": 1235,
    "一米": 1236,
    "开除": 1237,
    "暑假": 1238,
    "他爸": 1239,
    "宽洪": 1240,
    "刚到": 1241,
    "寒山": 1242,
    "对于": 1243,
    "邻居家": 1244,
    "弱弱": 1245,
    "村口": 1246,
    "废品": 1247,
    "鞋店": 1248,
    "趁": 1249,
    "5": 1250,
    "从小": 1251,
    "张嘴": 1252,
    "活动": 1253,
    "面包": 1254,
    "取名": 1255,
    "夏有": 1256,
    "别提": 1257,
    "气": 1258,
    "闺密": 1259,
    "然": 1260,
    "七八岁": 1261,
    "从来": 1262,
    "亲爱": 1263,
    "姑姑": 1264,
    "伸出": 1265,
    "我要": 1266,
    "半生": 1267,
    "一副": 1268,
    "窸": 1269,
    "号": 1270,
    "或": 1271,
    "女盆友": 1272,
    "纸巾": 1273,
    "大腿": 1274,
    "耐": 1275,
    "临": 1276,
    "语重心长": 1277,
    "搓": 1278,
    "我怕": 1279,
    "人事部": 1280,
    "标准": 1281,
    "想想": 1282,
    "两张": 1283,
    "入职": 1284,
    "腻": 1285,
    "厂里": 1286,
    "地下": 1287,
    "熟": 1288,
    "只要": 1289,
    "逗": 1290,
    "尝尝": 1291,
    "0": 1292,
    "就诊": 1293,
    "不断": 1294,
    "点着": 1295,
    "大方": 1296,
    "部长": 1297,
    "快递": 1298,
    "年龄": 1299,
    "道理": 1300,
    "开口": 1301,
    "猪": 1302,
    "节": 1303,
    "肩上": 1304,
    "期": 1305,
    "觉": 1306,
    "f": 1307,
    "小心翼翼": 1308,
    "歌歌": 1309,
    "快到": 1310,
    "一棵树": 1311,
    "刀": 1312,
    "卫生纸": 1313,
    "天师": 1314,
    "气得": 1315,
    "塞": 1316,
    "_": 1317,
    "点点头": 1318,
    "捎": 1319,
    "喝酒": 1320,
    "女妖": 1321,
    "寿衣": 1322,
    "间": 1323,
    "任何": 1324,
    "展示": 1325,
    "抹": 1326,
    "没敢": 1327,
    "材料": 1328,
    "用力": 1329,
    "约": 1330,
    "十块钱": 1331,
    "流口水": 1332,
    "炼制": 1333,
    "生活": 1334,
    "诊所": 1335,
    "几句": 1336,
    "大小": 1337,
    "碰见": 1338,
    "捣乱": 1339,
    "15": 1340,
    "停": 1341,
    "火": 1342,
    "呜": 1343,
    "害": 1344,
    "敢": 1345,
    "肚子疼": 1346,
    "表情": 1347,
    "下肚": 1348,
    "庙": 1349,
    "不怎么": 1350,
    "戳": 1351,
    "呐": 1352,
    "两次": 1353,
    "几下": 1354,
    "等到": 1355,
    "玩意": 1356,
    "转弯": 1357,
    "铁匠": 1358,
    "宝宝": 1359,
    "那头": 1360,
    "注意": 1361,
    "完年": 1362,
    "排队": 1363,
    "第三者": 1364,
    "房顶": 1365,
    "上交": 1366,
    "全程": 1367,
    "理发师": 1368,
    "逃": 1369,
    "故意": 1370,
    "理发": 1371,
    "毕竟": 1372,
    "共享": 1373,
    "希望": 1374,
    "抬起": 1375,
    "一大": 1376,
    "上岸": 1377,
    "刚要": 1378,
    "急忙": 1379,
    "冒": 1380,
    "校园": 1381,
    "呜呜": 1382,
    "客房": 1383,
    "试试看": 1384,
    "坐下": 1385,
    "悲": 1386,
    "基金": 1387,
    "光": 1388,
    "脱": 1389,
    "家长会": 1390,
    "中医": 1391,
    "爱新觉罗": 1392,
    "我会": 1393,
    "擅长": 1394,
    "哈": 1395,
    "惊呆": 1396,
    "浪漫": 1397,
    "干什么": 1398,
    "渐渐": 1399,
    "一套": 1400,
    "一顶": 1401,
    "上衣": 1402,
    "少": 1403,
    "叮嘱": 1404,
    "吼道": 1405,
    "布谷鸟": 1406,
    "不好意思": 1407,
    "传功": 1408,
    "车工": 1409,
    "一层": 1410,
    "张": 1411,
    "办": 1412,
    "标题": 1413,
    "三天": 1414,
    "捉": 1415,
    "全": 1416,
    "如何": 1417,
    "打牌": 1418,
    "枕头": 1419,
    "爸爸妈妈": 1420,
    "根": 1421,
    "a": 1422,
    "这辈子": 1423,
    "3": 1424,
    "看不到": 1425,
    "以身作则": 1426,
    "距离": 1427,
    "叠": 1428,
    "回家路上": 1429,
    "天生": 1430,
    "蚯蚓": 1431,
    "代理权": 1432,
    "短": 1433,
    "班上": 1434,
    "嚼": 1435,
    "配": 1436,
    "询问": 1437,
    "忧伤": 1438,
    "报": 1439,
    "传给": 1440,
    "一小": 1441,
    "将": 1442,
    "沾": 1443,
    "心理": 1444,
    "冷": 1445,
    "老白干": 1446,
    "运动鞋": 1447,
    "大喊": 1448,
    "要不是": 1449,
    "考验": 1450,
    "热": 1451,
    "走路": 1452,
    "葱": 1453,
    "哥们儿": 1454,
    "喷": 1455,
    "爹妈": 1456,
    "工资": 1457,
    "低": 1458,
    "生日": 1459,
    "兴奋": 1460,
    "四班": 1461,
    "抽出": 1462,
    "高中": 1463,
    "惹": 1464,
    "岁": 1465,
    "富": 1466,
    "视": 1467,
    "抽空": 1468,
    "少年": 1469,
    "声": 1470,
    "减压": 1471,
    "厉害": 1472,
    "凌晨": 1473,
    "送回": 1474,
    "千万": 1475,
    "压力": 1476,
    "城里": 1477,
    "捂脸": 1478,
    "棒子": 1479,
    "哪儿": 1480,
    "段时间": 1481,
    "洗手间": 1482,
    "神": 1483,
    "优秀": 1484,
    "有时候": 1485,
    "一遍": 1486,
    "抬头": 1487,
    "重复": 1488,
    "拍了拍": 1489,
    "车站": 1490,
    "回答": 1491,
    "程度": 1492,
    "》": 1493,
    "擤": 1494,
    "狼": 1495,
    "约会": 1496,
    "假": 1497,
    "经过": 1498,
    "大儿子": 1499,
    "分钟": 1500,
    "逍遥": 1501,
    "节目": 1502,
    "猪蹄": 1503,
    "好烦": 1504,
    "人不知": 1505,
    "高跟鞋": 1506,
    "装": 1507,
    "花落": 1508,
    "下楼": 1509,
    "肿": 1510,
    "贼": 1511,
    "主动": 1512,
    "过敏": 1513,
    "7": 1514,
    "我领": 1515,
    "《": 1516,
    "义行": 1517,
    "根本": 1518,
    "不得了": 1519,
    "我用": 1520,
    "猪头": 1521,
    "蹭": 1522,
    "突发奇想": 1523,
    "感动": 1524,
    "爪子": 1525,
    "没个": 1526,
    "挑": 1527,
    "体验": 1528,
    "晚饭": 1529,
    "闲着没事": 1530,
    "有钱": 1531,
    "每当": 1532,
    "小侄女": 1533,
    "十分": 1534,
    "是因为": 1535,
    "接个": 1536,
    "说白了": 1537,
    "些": 1538,
    "屁股": 1539,
    "组织": 1540,
    "闲着": 1541,
    "许久": 1542,
    "挣钱": 1543,
    "网恋": 1544,
    "位置": 1545,
    "哪有": 1546,
    "宰": 1547,
    "好人": 1548,
    "遇见": 1549,
    "座": 1550,
    "蟹": 1551,
    "帝王": 1552,
    "解开": 1553,
    "搞定": 1554,
    "狠揍": 1555,
    "广告": 1556,
    "并且": 1557,
    "剪刀": 1558,
    "再也": 1559,
    "😂": 1560,
    "大约": 1561,
    "昨天晚上": 1562,
    "一种": 1563,
    "同时": 1564,
    "曾经": 1565,
    "领养": 1566,
    "小区": 1567,
    "房东": 1568,
    "认为": 1569,
    "地说": 1570,
    "穿着": 1571,
    "几十块": 1572,
    "梨": 1573,
    "就让": 1574,
    "废书": 1575,
    "说起": 1576,
    "臭小子": 1577,
    "周围": 1578,
    "师父": 1579,
    "头上": 1580,
    "一千块": 1581,
    "静": 1582,
    "改不了": 1583,
    "小家伙": 1584,
    "习惯": 1585,
    "太快": 1586,
    "浑身": 1587,
    "奖状": 1588,
    "学习": 1589,
    "咱俩": 1590,
    "说法": 1591,
    "太好了": 1592,
    "三岁": 1593,
    "∽": 1594,
    "亲": 1595,
    "交了": 1596,
    "多次": 1597,
    "纸包": 1598,
    "嫌弃": 1599,
    "前排": 1600,
    "那次": 1601,
    "鱼缸": 1602,
    "油漆": 1603,
    "最大": 1604,
    "远": 1605,
    "互相": 1606,
    "内": 1607,
    "屡次": 1608,
    "两只": 1609,
    "插": 1610,
    "够": 1611,
    "拎": 1612,
    "卧槽": 1613,
    "同款": 1614,
    "办法": 1615,
    "打麻将": 1616,
    "风衣": 1617,
    "委屈": 1618,
    "证明": 1619,
    "回老家": 1620,
    "相": 1621,
    "增高": 1622,
    "一人": 1623,
    "退": 1624,
    "店员": 1625,
    "科目": 1626,
    "边上": 1627,
    "店": 1628,
    "反": 1629,
    "报名处": 1630,
    "耐心": 1631,
    "馅": 1632,
    "看来": 1633,
    "主持人": 1634,
    "自家": 1635,
    "摔": 1636,
    "扯开": 1637,
    "分手": 1638,
    "广东": 1639,
    "按": 1640,
    "响起": 1641,
    "脑子里": 1642,
    "马路边": 1643,
    "下手": 1644,
    "小张": 1645,
    "回事": 1646,
    "扶": 1647,
    "我能": 1648,
    "母老虎": 1649,
    "谈话": 1650,
    "一辆车": 1651,
    "渣": 1652,
    "晚": 1653,
    "唉": 1654,
    "捂住": 1655,
    "还行": 1656,
    "和尚": 1657,
    "小李": 1658,
    "酒店": 1659,
    "读": 1660,
    "蚊香": 1661,
    "货车": 1662,
    "忽然": 1663,
    "机会": 1664,
    "此时": 1665,
    "一根": 1666,
    "眼": 1667,
    "N": 1668,
    "出去玩": 1669,
    "算了吧": 1670,
    "好好": 1671,
    "骂人": 1672,
    "五六": 1673,
    "羡慕": 1674,
    "件": 1675,
    "恋人": 1676,
    "越来越": 1677,
    "怎么办": 1678,
    "墙上": 1679,
    "星期": 1680,
    "调皮": 1681,
    "一对": 1682,
    "库房": 1683,
    "说实话": 1684,
    "话题": 1685,
    "传来": 1686,
    "牙齿": 1687,
    "打算": 1688,
    "表现": 1689,
    "及": 1690,
    "酒味": 1691,
    "死活": 1692,
    "下属": 1693,
    "宠": 1694,
    "鞋印": 1695,
    "；": 1696,
    "白莲花": 1697,
    "要钱": 1698,
    "打包": 1699,
    "输": 1700,
    "周末": 1701,
    "边想": 1702,
    "不紧不慢": 1703,
    "实习": 1704,
    "插话": 1705,
    "怀过": 1706,
    "太能": 1707,
    "苗": 1708,
    "打疫": 1709,
    "帐": 1710,
    "筱悦": 1711,
    "降血脂": 1712,
    "jc": 1713,
    "孕": 1714,
    "温度": 1715,
    "三十度": 1716,
    "科学依据": 1717,
    "中心": 1718,
    "模具": 1719,
    "走近": 1720,
    "普外": 1721,
    "唯一": 1722,
    "现场": 1723,
    "快速": 1724,
    "儿童节": 1725,
    "玩具": 1726,
    "琢磨": 1727,
    "学业": 1728,
    "为重": 1729,
    "没招": 1730,
    "招工": 1731,
    "外出": 1732,
    "包宿": 1733,
    "2.14": 1734,
    "上网": 1735,
    "盐": 1736,
    "没收": 1737,
    "细问": 1738,
    "全家人": 1739,
    "打着": 1740,
    "小孩儿": 1741,
    "3.8": 1742,
    "成长": 1743,
    "痛哭流涕": 1744,
    "弟入": 1745,
    "进村": 1746,
    "储藏": 1747,
    "笑笑": 1748,
    "究竟": 1749,
    "多么": 1750,
    "跳舞": 1751,
    "送给": 1752,
    "巡逻": 1753,
    "唠嗑": 1754,
    "闲聊": 1755,
    "五百元": 1756,
    "米": 1757,
    "无表情": 1758,
    "村里人": 1759,
    "下车": 1760,
    "没空": 1761,
    "出色": 1762,
    "挺远": 1763,
    "开出": 1764,
    "鸣笛": 1765,
    "时光": 1766,
    "看不懂": 1767,
    "疯子": 1768,
    "搀": 1769,
    "打车": 1770,
    "明查暗访": 1771,
    "钓": 1772,
    "偶遇": 1773,
    "完鱼": 1774,
    "榆木脑袋": 1775,
    "动静": 1776,
    "酒吧": 1777,
    "臭屁": 1778,
    "亲手": 1779,
    "臭": 1780,
    "改成": 1781,
    "而已": 1782,
    "跟班": 1783,
    "待会儿": 1784,
    "升": 1785,
    "缺德": 1786,
    "老毛": 1787,
    "三年级": 1788,
    "半小时": 1789,
    "大概": 1790,
    "戴着": 1791,
    "一圈": 1792,
    "威力": 1793,
    "楼主": 1794,
    "眼镜": 1795,
    "受不了": 1796,
    "合照": 1797,
    "破": 1798,
    "无奈": 1799,
    "第一份": 1800,
    "边境": 1801,
    "邻国": 1802,
    "做起": 1803,
    "失神": 1804,
    "小眼": 1805,
    "边贸": 1806,
    "眼见": 1807,
    "吹": 1808,
    "大眼瞪": 1809,
    "没关系": 1810,
    "破产": 1811,
    "使劲": 1812,
    "缝": 1813,
    "满上": 1814,
    "手上": 1815,
    "失联": 1816,
    "做梦": 1817,
    "气不打": 1818,
    "香": 1819,
    "往外": 1820,
    "冷汗": 1821,
    "惊醒": 1822,
    "吼": 1823,
    "恶梦": 1824,
    "从床": 1825,
    "久": 1826,
    "没钱": 1827,
    "镇上": 1828,
    "爱去": 1829,
    "这时候": 1830,
    "呛": 1831,
    "冰棍": 1832,
    "奶油": 1833,
    "两根": 1834,
    "一处": 1835,
    "挡住": 1836,
    "危险": 1837,
    "一名": 1838,
    "怎么样": 1839,
    "尝到": 1840,
    "这才": 1841,
    "跑不了": 1842,
    "地步": 1843,
    "没用": 1844,
    "接生": 1845,
    "别说": 1846,
    "百般无奈": 1847,
    "到家时": 1848,
    "炸": 1849,
    "承受": 1850,
    "扯": 1851,
    "留着": 1852,
    "站住": 1853,
    "口": 1854,
    "冷笑": 1855,
    "讲真": 1856,
    "慌": 1857,
    "操作": 1858,
    "事业": 1859,
    "网络": 1860,
    "两人": 1861,
    "机灵": 1862,
    "硬": 1863,
    "新人": 1864,
    "天赋": 1865,
    "不归路": 1866,
    "舍不得": 1867,
    "与众不同": 1868,
    "爬山": 1869,
    "野菜": 1870,
    "翻白": 1871,
    "淡淡的": 1872,
    "嘴里": 1873,
    "一生": 1874,
    "野": 1875,
    "烤箱": 1876,
    "瓷娃娃": 1877,
    "朝": 1878,
    "一刻": 1879,
    "早稻田大学": 1880,
    "浪费": 1881,
    "美好": 1882,
    "深海": 1883,
    "阿拉斯加": 1884,
    "来自": 1885,
    "以防": 1886,
    "养老": 1887,
    "送终": 1888,
    "据说": 1889,
    "半只": 1890,
    "尝尝鲜": 1891,
    "想带": 1892,
    "咩": 1893,
    "而是": 1894,
    "国外": 1895,
    "提亲": 1896,
    "托人": 1897,
    "一股": 1898,
    "黄花菜": 1899,
    "傻眼": 1900,
    "一千万": 1901,
    "截粗": 1902,
    "相信": 1903,
    "看电视": 1904,
    "笔记本": 1905,
    "企业": 1906,
    "奶爸": 1907,
    "胸大": 1908,
    "耍": 1909,
    "然而": 1910,
    "先是": 1911,
    "失忆": 1912,
    "顺利": 1913,
    "故事": 1914,
    "有利于": 1915,
    "恢复": 1916,
    "顺带": 1917,
    "叮叮": 1918,
    "几声": 1919,
    "哭腔": 1920,
    "小型": 1921,
    "欢": 1922,
    "炉": 1923,
    "炼丹": 1924,
    "来说": 1925,
    "完全": 1926,
    "台": 1927,
    "一道": 1928,
    "汤": 1929,
    "无论": 1930,
    "一通": 1931,
    "尝": 1932,
    "吃完饭": 1933,
    "锈": 1934,
    "表皮": 1935,
    "钢管": 1936,
    "磨掉": 1937,
    "打磨": 1938,
    "走上": 1939,
    "期末": 1940,
    "二": 1941,
    "入口": 1942,
    "亲戚": 1943,
    "死里整": 1944,
    "赞同": 1945,
    "男神": 1946,
    "舀": 1947,
    "内心": 1948,
    "诱惑": 1949,
    "棍子": 1950,
    "食材": 1951,
    "娶": 1952,
    "炖煮": 1953,
    "鸡屎": 1954,
    "高压": 1955,
    "狠": 1956,
    "七七四十": 1957,
    "煲汤": 1958,
    "土": 1959,
    "材质": 1960,
    "别来": 1961,
    "非": 1962,
    "一群": 1963,
    "树懒": 1964,
    "进屋": 1965,
    "一碗": 1966,
    "夜": 1967,
    "剥开": 1968,
    "老年斑": 1969,
    "粽子": 1970,
    "没开": 1971,
    "变慢": 1972,
    "一路": 1973,
    "亲身经历": 1974,
    "色": 1975,
    "痞子": 1976,
    "一个样": 1977,
    "多慢": 1978,
    "奇": 1979,
    "销售": 1980,
    "重要": 1981,
    "比颜值": 1982,
    "失去": 1983,
    "经人": 1984,
    "换上": 1985,
    "点点": 1986,
    "冷冷的": 1987,
    "挺高": 1988,
    "预览": 1989,
    "片子": 1990,
    "那边": 1991,
    "调色": 1992,
    "四十": 1993,
    "耳朵": 1994,
    "四": 1995,
    "个头": 1996,
    "si": 1997,
    "变": 1998,
    "一口袋": 1999,
    "生病": 2000,
    "亮": 2001,
    "病好": 2002,
    "这事": 2003,
    "一大群": 2004,
    "几千": 2005,
    "醉卧": 2006,
    "膝": 2007,
    "爆米花": 2008,
    "迅速": 2009,
    "他来": 2010,
    "附近": 2011,
    "买车": 2012,
    "年夜饭": 2013,
    "教课": 2014,
    "顿饭": 2015,
    "^": 2016,
    "昨天下午": 2017,
    "艾玛": 2018,
    "道菜": 2019,
    "挂科": 2020,
    "梦里": 2021,
    "噩梦": 2022,
    "学渣": 2023,
    "兔": 2024,
    "↘": 2025,
    "侧翻": 2026,
    "对饮": 2027,
    "做到": 2028,
    "我想": 2029,
    "不该": 2030,
    "铺盖": 2031,
    "哥嫂": 2032,
    "胖丫对": 2033,
    "架": 2034,
    "先考": 2035,
    "资料": 2036,
    "学车": 2037,
    "通气": 2038,
    "闷闷不乐": 2039,
    "抹抹": 2040,
    "更加": 2041,
    "一盘": 2042,
    "纳闷": 2043,
    "纹丝不动": 2044,
    "连人带": 2045,
    "算了": 2046,
    "扭扭捏捏": 2047,
    "浇": 2048,
    "大雨": 2049,
    "弟弟": 2050,
    "买好": 2051,
    "苗条": 2052,
    "讪讪": 2053,
    "笑了笑": 2054,
    "网上": 2055,
    "好喝": 2056,
    "红绿灯": 2057,
    "免费": 2058,
    "牌牌": 2059,
    "旁有": 2060,
    "饮料": 2061,
    "礼物": 2062,
    "吃点": 2063,
    "服务区": 2064,
    "长途": 2065,
    "孙子": 2066,
    "叔": 2067,
    "人行道": 2068,
    "女性": 2069,
    "失败": 2070,
    "哄抢": 2071,
    "吃糖": 2072,
    "大全": 2073,
    "她俩": 2074,
    "一百块": 2075,
    "麻局": 2076,
    "吹牛": 2077,
    "开玩笑": 2078,
    "合影": 2079,
    "追上": 2080,
    "好几分钟": 2081,
    "女方": 2082,
    "俺们": 2083,
    "缓缓": 2084,
    "斗争": 2085,
    "素颜自": 2086,
    "美颜": 2087,
    "采访": 2088,
    "记者": 2089,
    "同情": 2090,
    "百科": 2091,
    "零钱": 2092,
    "没洗": 2093,
    "颤颤巍巍": 2094,
    "退役": 2095,
    "空军": 2096,
    "床": 2097,
    "地勤": 2098,
    "(": 2099,
    "飞机": 2100,
    "尾翼": 2101,
    "废料": 2102,
    "19": 2103,
    "扫": 2104,
    "用法": 2105,
    "菜刀": 2106,
    "心照不宣": 2107,
    "右脚": 2108,
    "这鞋": 2109,
    "三次": 2110,
    "越": 2111,
    "肆无忌惮": 2112,
    "小屁孩": 2113,
    "喷药": 2114,
    "回头": 2115,
    "车正": 2116,
    "哆嗦": 2117,
    "本能": 2118,
    "!": 2119,
    "绕": 2120,
    "苍蝇": 2121,
    "十个": 2122,
    "教学楼": 2123,
    "家用": 2124,
    "里装": 2125,
    "脸红": 2126,
    "补贴": 2127,
    "不如": 2128,
    "手掌": 2129,
    "家庭": 2130,
    "挣": 2131,
    "心地善良": 2132,
    "以上": 2133,
    "安利": 2134,
    "唉声叹气": 2135,
    "越想": 2136,
    "油滑": 2137,
    "脱发": 2138,
    "脱单": 2139,
    "说好": 2140,
    "油腻": 2141,
    "挤": 2142,
    "带我去": 2143,
    "发脾气": 2144,
    "好大": 2145,
    "离开": 2146,
    "屎": 2147,
    "早就": 2148,
    "95": 2149,
    "催": 2150,
    "见到": 2151,
    "挣脱": 2152,
    "梦": 2153,
    "无所不能": 2154,
    "升天": 2155,
    "受不来": 2156,
    "两者": 2157,
    "细占": 2158,
    "不为过": 2159,
    "法拉利": 2160,
    "脏": 2161,
    "启动": 2162,
    "秒": 2163,
    "影子": 2164,
    "趴着": 2165,
    "院子": 2166,
    "萌宝": 2167,
    "精": 2168,
    "苦": 2169,
    "算": 2170,
    "当天": 2171,
    "小人": 2172,
    "瓜": 2173,
    "说个": 2174,
    "阑尾炎": 2175,
    "手术": 2176,
    "伤口": 2177,
    "那款": 2178,
    "KO": 2179,
    "跑车": 2180,
    "海里": 2181,
    "啃老族": 2182,
    "味": 2183,
    "劈里啪啦": 2184,
    "貌美": 2185,
    "找对象": 2186,
    "不来": 2187,
    "拦": 2188,
    "持有": 2189,
    "管制": 2190,
    "刀具": 2191,
    "有刀": 2192,
    "帅气": 2193,
    "满": 2194,
    "风雨": 2195,
    "阴盛阳衰": 2196,
    "吱声": 2197,
    "观赏鱼": 2198,
    "墨水": 2199,
    "没养": 2200,
    "红墨水": 2201,
    "』": 2202,
    "请教": 2203,
    "保持": 2204,
    "表示": 2205,
    "轻轻": 2206,
    "大姑": 2207,
    "矛盾": 2208,
    "超脱": 2209,
    "婚后": 2210,
    "夸": 2211,
    "肚子": 2212,
    "空欢喜": 2213,
    "追求": 2214,
    "厉声": 2215,
    "窃喜": 2216,
    "纸篓": 2217,
    "之": 2218,
    "满满": 2219,
    "『": 2220,
    "诵经": 2221,
    "念佛": 2222,
    "奇怪": 2223,
    "不下": 2224,
    "脸用": 2225,
    "随口": 2226,
    "丰": 2227,
    "好意思": 2228,
    "问是": 2229,
    "霜": 2230,
    "贾玲": 2231,
    "瓶丰": 2232,
    "新买": 2233,
    "死沉": 2234,
    "动手": 2235,
    "陶": 2236,
    "夫人": 2237,
    "网游": 2238,
    "崇拜": 2239,
    "勾引": 2240,
    "说不出": 2241,
    "以及": 2242,
    "盟里": 2243,
    "院里": 2244,
    "梨子": 2245,
    "绚烂": 2246,
    "结婚的人": 2247,
    "说干就干": 2248,
    "约定": 2249,
    "显然": 2250,
    "类型": 2251,
    "条": 2252,
    "青春": 2253,
    "那树": 2254,
    "胖丫把": 2255,
    "个人": 2256,
    "运动": 2257,
    "不说": 2258,
    "呼噜": 2259,
    "小侄": 2260,
    "残存": 2261,
    "可乐": 2262,
    "梨树": 2263,
    "孤独": 2264,
    "盼": 2265,
    "不像": 2266,
    "出租车": 2267,
    "凉水": 2268,
    "雪糕": 2269,
    "狠招": 2270,
    "想了个": 2271,
    "一半": 2272,
    "同一个": 2273,
    "慢慢": 2274,
    "不然": 2275,
    "基本": 2276,
    "牙疼": 2277,
    "晚安": 2278,
    "忐忑": 2279,
    "祝": 2280,
    "这回": 2281,
    "可想而知": 2282,
    "太漂亮": 2283,
    "摆弄": 2284,
    "运果": 2285,
    "袁大头": 2286,
    "已婚": 2287,
    "孪生": 2288,
    "发型": 2289,
    "关": 2290,
    "前后": 2291,
    "下蛋": 2292,
    "养只": 2293,
    "唐僧": 2294,
    "袈裟": 2295,
    "要养": 2296,
    "电视机": 2297,
    "闹": 2298,
    "有放": 2299,
    "一部": 2300,
    "代步车": 2301,
    "第一辆": 2302,
    "新车": 2303,
    "寻思": 2304,
    "晃悠": 2305,
    "没卖": 2306,
    "人来": 2307,
    "一面": 2308,
    "创业": 2309,
    "往前": 2310,
    "认真学习": 2311,
    "变得": 2312,
    "有趣": 2313,
    "风吹草动": 2314,
    "吸引": 2315,
    "样貌": 2316,
    "手机卡": 2317,
    "沉默": 2318,
    "七": 2319,
    "右边": 2320,
    "摔倒": 2321,
    "四年": 2322,
    "从没": 2323,
    "买过": 2324,
    "卫生巾": 2325,
    "前天": 2326,
    "859": 2327,
    "萌萌": 2328,
    "抢到": 2329,
    "般的": 2330,
    "抱住": 2331,
    "辅导员": 2332,
    "每人": 2333,
    "可不是": 2334,
    "感叹": 2335,
    "下辈子": 2336,
    "嫁": 2337,
    "骑车": 2338,
    "武大郎": 2339,
    "戴眼镜": 2340,
    "不但": 2341,
    "炊饼": 2342,
    "略有": 2343,
    "聚餐": 2344,
    "水电": 2345,
    "带徒弟": 2346,
    "晃进": 2347,
    "低头": 2348,
    "领": 2349,
    "年末": 2350,
    "眼眶": 2351,
    "泛红": 2352,
    "住处": 2353,
    "来发": 2354,
    "卷子": 2355,
    "会少": 2356,
    "打扑克": 2357,
    "马尾": 2358,
    "上身": 2359,
    "修长": 2360,
    "淡蓝色": 2361,
    "牛仔裤": 2362,
    "一楼": 2363,
    "新生": 2364,
    "一整天": 2365,
    "大一": 2366,
    "看不出来": 2367,
    "绝对": 2368,
    "花生": 2369,
    "体质": 2370,
    "调离": 2371,
    "例行公事": 2372,
    "无辜": 2373,
    "印": 2374,
    "开个": 2375,
    "欢送会": 2376,
    "婷婷": 2377,
    "记挂": 2378,
    "万分": 2379,
    "不舍": 2380,
    "个子": 2381,
    "多数": 2382,
    "烫": 2383,
    "衣兜": 2384,
    "语文": 2385,
    "要考": 2386,
    "上床": 2387,
    "染": 2388,
    "做完作业": 2389,
    "误会": 2390,
    "染发": 2391,
    "太丑": 2392,
    "力度": 2393,
    "忙前忙后": 2394,
    "安心": 2395,
    "送亲": 2396,
    "得意": 2397,
    "要死": 2398,
    "小奶": 2399,
    "直": 2400,
    "两盒": 2401,
    "强": 2402,
    "得到": 2403,
    "无家可归": 2404,
    "保护": 2405,
    "分别": 2406,
    "母上": 2407,
    "缺": 2408,
    "左边": 2409,
    "备注": 2410,
    "金黄": 2411,
    "第一条": 2412,
    "互加": 2413,
    "我薇信": 2414,
    "一座": 2415,
    "股": 2416,
    "新修": 2417,
    "打屁": 2418,
    "古韵": 2419,
    "古风": 2420,
    "一个个": 2421,
    "越建越": 2422,
    "活生生": 2423,
    "建筑": 2424,
    "壮": 2425,
    "纠结": 2426,
    "孤心傲": 2427,
    "功夫": 2428,
    "问问": 2429,
    "脾气": 2430,
    "简单": 2431,
    "粗暴": 2432,
    "打骂": 2433,
    "爱心": 2434,
    "贤淑": 2435,
    "言传身教": 2436,
    "安静": 2437,
    "静淑": 2438,
    "颤": 2439,
    "泪水": 2440,
    "盈满": 2441,
    "玩家": 2442,
    "网络游戏": 2443,
    "性格": 2444,
    "不服输": 2445,
    "凌虐": 2446,
    "苦练": 2447,
    "恨不得": 2448,
    "烧": 2449,
    "发个": 2450,
    "感个": 2451,
    "兽性大发": 2452,
    "当妈": 2453,
    "溜": 2454,
    "男演员": 2455,
    "宝贝女儿": 2456,
    "澡": 2457,
    "没人": 2458,
    "干呕": 2459,
    "开会": 2460,
    "董事": 2461,
    "洗完": 2462,
    "注视": 2463,
    "所": 2464,
    "跪下": 2465,
    "台阶": 2466,
    "我刚": 2467,
    "六岁": 2468,
    "吐槽": 2469,
    "撒": 2470,
    "输卵管": 2471,
    "超级": 2472,
    "导游": 2473,
    "图书馆": 2474,
    "将来": 2475,
    "相中": 2476,
    "专心": 2477,
    "眼神": 2478,
    "泡澡": 2479,
    "犊子": 2480,
    "饿": 2481,
    "听歌": 2482,
    "爷爷奶奶": 2483,
    "相继": 2484,
    "深刻": 2485,
    "入殓": 2486,
    "没想": 2487,
    "悠闲": 2488,
    "帅哥": 2489,
    "半岁": 2490,
    "报大": 2491,
    "新谈": 2492,
    "款": 2493,
    "贷到": 2494,
    "趁机": 2495,
    "到时候": 2496,
    "拉小": 2497,
    "妇科": 2498,
    "左侧": 2499,
    "嗖": 2500,
    "皱纹": 2501,
    "亲密": 2502,
    "干鸡": 2503,
    "兵王": 2504,
    "靠": 2505,
    "007": 2506,
    "吵架": 2507,
    "吵急": 2508,
    "示弱": 2509,
    "情侣": 2510,
    "单间": 2511,
    "捡起": 2512,
    "被褥": 2513,
    "垫子": 2514,
    "仿佛": 2515,
    "提出": 2516,
    "效益": 2517,
    "连忙": 2518,
    "到底": 2519,
    "女滴": 2520,
    "飘": 2521,
    "上海": 2522,
    "旅游": 2523,
    "旅游团": 2524,
    "男女": 2525,
    "形影不离": 2526,
    "一时间": 2527,
    "结余": 2528,
    "不少": 2529,
    "澡堂子": 2530,
    "配制": 2531,
    "秘方": 2532,
    "岳母": 2533,
    "十几年来": 2534,
    "睡意": 2535,
    "朦胧": 2536,
    "人缘": 2537,
    "四点": 2538,
    "性价比": 2539,
    "一顿饭": 2540,
    "憋不住": 2541,
    "导致": 2542,
    "狗子": 2543,
    "脏话": 2544,
    "11": 2545,
    "开店": 2546,
    "饮水机": 2547,
    "送人": 2548,
    "怎": 2549,
    "空桶": 2550,
    "角落里": 2551,
    "闲置": 2552,
    "十几分钟": 2553,
    "改": 2554,
    "前阵": 2555,
    "只顾": 2556,
    "万一": 2557,
    "9": 2558,
    "6": 2559,
    "疯狂": 2560,
    "我拉进": 2561,
    "猴": 2562,
    "猖獗": 2563,
    "本着": 2564,
    "哀乐": 2565,
    "正好": 2566,
    "喝咖啡": 2567,
    "真人": 2568,
    "拼": 2569,
    "多多": 2570,
    "啥时候": 2571,
    "逛": 2572,
    "姥姥": 2573,
    "一换": 2574,
    "遭": 2575,
    "一千": 2576,
    "拾金不昧": 2577,
    "来电": 2578,
    "感知": 2579,
    "老娘": 2580,
    "一颤": 2581,
    "背景": 2582,
    "闲得": 2583,
    "闲": 2584,
    "S": 2585,
    "长相": 2586,
    "身子": 2587,
    "骚扰": 2588,
    "标记": 2589,
    "含着泪": 2590,
    "交往": 2591,
    "娘": 2592,
    "这不刚": 2593,
    "扛": 2594,
    "医学专业": 2595,
    "肌肉": 2596,
    "选上": 2597,
    "村长": 2598,
    "义": 2599,
    "航拍": 2600,
    "无人机": 2601,
    "缺点": 2602,
    "五百块": 2603,
    "故障": 2604,
    "扣": 2605,
    "不亦乐乎": 2606,
    "初二": 2607,
    "包进": 2608,
    "一千元": 2609,
    "早有": 2610,
    "外公": 2611,
    "校长": 2612,
    "一问": 2613,
    "作弊": 2614,
    "尿壶": 2615,
    "本石锅": 2616,
    "三宵": 2617,
    "因": 2618,
    "太皮": 2619,
    "成名": 2620,
    "接近": 2621,
    "演": 2622,
    "抽泣": 2623,
    "淘气": 2624,
    "螺丝": 2625,
    "教育片": 2626,
    "惨叫": 2627,
    "黑板刷": 2628,
    "一番": 2629,
    "做事": 2630,
    "才能": 2631,
    "辅助线": 2632,
    "十多天": 2633,
    "半截": 2634,
    "烟云": 2635,
    "马桶盖": 2636,
    "马桶": 2637,
    "门锁": 2638,
    "看封": 2639,
    "有天": 2640,
    "四段": 2641,
    "右": 2642,
    "比划": 2643,
    "年货": 2644,
    "码": 2645,
    "疫情": 2646,
    "左": 2647,
    "扎针": 2648,
    "跆拳道": 2649,
    "看起来": 2650,
    "小儿子": 2651,
    "来选": 2652,
    "顶天": 2653,
    "香喷喷": 2654,
    "提醒": 2655,
    "人工": 2656,
    "街边": 2657,
    "陪衬": 2658,
    "他俩": 2659,
    "六四": 2660,
    "咱": 2661,
    "用不上": 2662,
    "不看": 2663,
    "昏昏": 2664,
    "看防": 2665,
    "长到": 2666,
    "士多店": 2667,
    "长得算": 2668,
    "普通": 2669,
    "紧身": 2670,
    "愈发": 2671,
    "年纪": 2672,
    "轮休": 2673,
    "跑步": 2674,
    "招呼": 2675,
    "咔嚓": 2676,
    "凳子": 2677,
    "午睡": 2678,
    "上前": 2679,
    "枂": 2680,
    "夹菜": 2681,
    "零食": 2682,
    "割": 2683,
    "摊点": 2684,
    "照面": 2685,
    "霸": 2686,
    "每位": 2687,
    "38": 2688,
    "几家": 2689,
    "二个": 2690,
    "尺码": 2691,
    "傍晚": 2692,
    "郊区": 2693,
    "情绪": 2694,
    "打人": 2695,
    "变坏": 2696,
    "客户": 2697,
    "一初": 2698,
    "保安": 2699,
    "几道菜": 2700,
    "不肯": 2701,
    "溜达": 2702,
    "沦落": 2703,
    "实诚": 2704,
    "历史": 2705,
    "几十年": 2706,
    "腰间": 2707,
    "值": 2708,
    "白班": 2709,
    "一趟": 2710,
    "答案": 2711,
    "旅店": 2712,
    "常常": 2713,
    "小姑娘": 2714,
    "杨": 2715,
    "一个多月": 2716,
    "进门": 2717,
    "待久": 2718,
    "现有": 2719,
    "辅导": 2720,
    "不争气": 2721,
    "强压怒火": 2722,
    "我生": 2723,
    "分工": 2724,
    "哪点": 2725,
    "今早": 2726,
    "些许": 2727,
    "反问": 2728,
    "先救": 2729,
    "水里": 2730,
    "临走前": 2731,
    "注意安全": 2732,
    "锁好": 2733,
    "门窗": 2734,
    "出生": 2735,
    "农历": 2736,
    "在外": 2737,
    "七月": 2738,
    "十四": 2739,
    "阴气": 2740,
    "不远处": 2741,
    "太重": 2742,
    "起名叫": 2743,
    "养猫": 2744,
    "疯": 2745,
    "透": 2746,
    "高考": 2747,
    "好点": 2748,
    "一段时间": 2749,
    "先养": 2750,
    "姐姐": 2751,
    "游乐场": 2752,
    "人山人海": 2753,
    "排长队": 2754,
    "一扭": 2755,
    "wifi": 2756,
    "半": 2757,
    "灬": 2758,
    "嫌累": 2759,
    "流行": 2760,
    "两家": 2761,
    "葡萄": 2762,
    "红颜色": 2763,
    "度": 2764,
    "匹配": 2765,
    "吃饱": 2766,
    "特": 2767,
    "聊到": 2768,
    "大喜事": 2769,
    "不带": 2770,
    "思考": 2771,
    "答道": 2772,
    "升官发财": 2773,
    "爱玩": 2774,
    "一战": 2775,
    "全世界": 2776,
    "操场上": 2777,
    "老中医": 2778,
    "气愤": 2779,
    "绑": 2780,
    "提心吊胆": 2781,
    "凡是": 2782,
    "第一关": 2783,
    "飙车": 2784,
    "八岁": 2785,
    "拍拖": 2786,
    "洗胃": 2787,
    "待遇": 2788,
    "网": 2789,
    "吹嘘": 2790,
    "一想": 2791,
    "剪短": 2792,
    "太长": 2793,
    "刨": 2794,
    "古老": 2795,
    "晚自习": 2796,
    "高二": 2797,
    "闷": 2798,
    "里边": 2799,
    "舅舅": 2800,
    "家传": 2801,
    "慢点": 2802,
    "俗话": 2803,
    "鸡肉": 2804,
    "摸不着": 2805,
    "功": 2806,
    "看不见": 2807,
    "切记": 2808,
    "赔": 2809,
    "掉下来": 2810,
    "错": 2811,
    "双排": 2812,
    "下巴": 2813,
    "欺负": 2814,
    "双手": 2815,
    "我奶": 2816,
    "不怕": 2817,
    "镜子": 2818,
    "侄女": 2819,
    "甘蔗": 2820,
    "节日": 2821,
    "十分钟": 2822,
    "套路": 2823,
    "挨个": 2824,
    "纸片": 2825,
    "39": 2826,
    "暗喜": 2827,
    "娃娃": 2828,
    "石凳": 2829,
    "偷喝": 2830,
    "call": 2831,
    "衣橱": 2832,
    "从那以后": 2833,
    "机": 2834,
    "目标": 2835,
    "22": 2836,
    "次日": 2837,
    "深情": 2838,
    "黑暗": 2839,
    "没醒": 2840,
    "仁兄": 2841,
    "惊奇": 2842,
    "BB机": 2843,
    "脸说": 2844,
    "写字": 2845,
    "一早": 2846,
    "怒": 2847,
    "怒火冲天": 2848,
    "还放": 2849,
    "树下": 2850,
    "欠": 2851,
    "算钱": 2852,
    "公园": 2853,
    "快过": 2854,
    "不久": 2855,
    "黑字": 2856,
    "组": 2857,
    "词": 2858,
    "周过": 2859,
    "一大家子": 2860,
    "仔细": 2861,
    "保守": 2862,
    "仍": 2863,
    "恰逢": 2864,
    "出嫁": 2865,
    "顺产": 2866,
    "转让": 2867,
    "很着急": 2868,
    "大白于天下": 2869,
    "一长": 2870,
    "底下": 2871,
    "说出": 2872,
    "敌敌畏": 2873,
    "我带": 2874,
    "网坏": 2875,
    "追剧": 2876,
    "丶": 2877,
    "家小": 2878,
    "哎呀": 2879,
    "电扇": 2880,
    "语气": 2881,
    "单车": 2882,
    "大冷": 2883,
    "吹泡泡": 2884,
    "同学聚会": 2885,
    "监狱长": 2886,
    "〉": 2887,
    "监狱": 2888,
    "嗓子疼": 2889,
    "爽快": 2890,
    "拿点": 2891,
    "〈": 2892,
    "害羞": 2893,
    "舌头": 2894,
    "伸": 2895,
    "借着": 2896,
    "见个面": 2897,
    "地面": 2898,
    "开放": 2899,
    "二孩": 2900,
    "自行车": 2901,
    "睡不着": 2902,
    "不解": 2903,
    "扇子": 2904,
    "其": 2905,
    "纪": 2906,
    "九头": 2907,
    "欣然同意": 2908,
    "自驾游": 2909,
    "一日": 2910,
    "没上": 2911,
    "牌": 2912,
    "大大咧咧": 2913,
    "相同": 2914,
    "得瑟": 2915,
    "姐刚": 2916,
    "念": 2917,
    "念念": 2918,
    "隐约": 2919,
    "捧": 2920,
    "160": 2921,
    "180": 2922,
    "一大堆": 2923,
    "丧偶": 2924,
    "下雨": 2925,
    "春风": 2926,
    "坚持不懈": 2927,
    "怀上": 2928,
    "可惜": 2929,
    "门面": 2930,
    "指": 2931,
    "显示": 2932,
    "找个": 2933,
    "人间": 2934,
    "墙围子": 2935,
    "裙": 2936,
    "这话": 2937,
    "几罐": 2938,
    "搞好": 2939,
    "小表弟": 2940,
    "运": 2941,
    "一掌": 2942,
    "傻": 2943,
    "关键": 2944,
    ".....": 2945,
    "转给": 2946,
    "盘腿": 2947,
    "包烟": 2948,
    "护法": 2949,
    "打扰": 2950,
    "水泡": 2951,
    "说瞎话": 2952,
    "身后": 2953,
    "写给": 2954,
    "说来": 2955,
    "一时": 2956,
    "成语": 2957,
    "眉头": 2958,
    "蹙": 2959,
    "写下": 2960,
    "无": 2961,
    "七天": 2962,
    "这不写": 2963,
    "售后": 2964,
    "非要": 2965,
    "外婆家": 2966,
    "活到": 2967,
    "忠告": 2968,
    "通常": 2969,
    "留点": 2970,
    "理论": 2971,
    "客服": 2972,
    "二货": 2973,
    "绝": 2974,
    "一家人": 2975,
    "搓衣板": 2976,
    "漆黑": 2977,
    "一查": 2978,
    "夫妻俩": 2979,
    "喝茶": 2980,
    "姐夫": 2981,
    "怀里": 2982,
    "素有": 2983,
    "冷场": 2984,
    "王之称": 2985,
    "避免": 2986,
    "建了": 2987,
    "拉入": 2988,
    "群中": 2989,
    "回应": 2990,
    "会上": 2991,
    "但凡": 2992,
    "分床": 2993,
    "新娘": 2994,
    "新郎": 2995,
    "10%": 2996,
    "夫妻关系": 2997,
    "老爷爷": 2998,
    "回忆": 2999,
    "严肃": 3000,
    "五颜六色": 3001,
    "TM": 3002,
    "办公": 3003,
    "老停": 3004,
    "细细的": 3005,
    "眼睁睁": 3006,
    "十岁": 3007,
    "门铃": 3008,
    "能活": 3009,
    "监控": 3010,
    "狡辩": 3011,
    "屁颠": 3012,
    "龙": 3013,
    "白色": 3014,
    "走边": 3015,
    "乐": 3016,
    "报官": 3017,
    "打趣": 3018,
    "属虎": 3019,
    "助理": 3020,
    "一言不合": 3021,
    "折腾": 3022,
    "理想": 3023,
    "交涉": 3024,
    "淘米": 3025,
    "赶": 3026,
    "垃圾桶": 3027,
    "这儿": 3028,
    "小喇叭": 3029,
    "巧": 3030,
    "退烧": 3031,
    "晨练": 3032,
    "家门": 3033,
    "兴冲冲": 3034,
    "县城": 3035,
    "面条": 3036,
    "喵": 3037,
    "抓娃": 3038,
    "里里外外": 3039,
    "随手": 3040,
    "外套": 3041,
    "体温": 3042,
    "路灯": 3043,
    "一度": 3044,
    "炒": 3045,
    "女主角": 3046,
    "输水": 3047,
    "八卦": 3048,
    "插足": 3049,
    "馒头": 3050,
    "75%": 3051,
    "嚷嚷": 3052,
    "窣窣": 3053,
    "一声不吭": 3054,
    "作响": 3055,
    "保洁": 3056,
    "邻村": 3057,
    "行政": 3058,
    "刹车": 3059,
    "分居": 3060,
    "寒假作业": 3061,
    "虽然": 3062,
    "发高烧": 3063,
    "公交车": 3064,
    "教导": 3065,
    "尊老爱幼": 3066,
    "享受": 3067,
    "一堆": 3068,
    "传统美德": 3069,
    "让座": 3070,
    "15%": 3071,
    "烟花爆竹": 3072,
    "麻利": 3073,
    "废纸": 3074,
    "心烦": 3075,
    "电线": 3076,
    "清晨": 3077,
    "过日子": 3078,
    "影响": 3079,
    "年级": 3080,
    "微微": 3081,
    "班任": 3082,
    "x5": 3083,
    "好家伙": 3084,
    "机场": 3085,
    "宿管": 3086,
    "同桌": 3087,
    "时比": 3088,
    "读书": 3089,
    "妹": 3090,
    "驾校": 3091,
    "自从": 3092,
    "蛋蛋": 3093,
    "束缚": 3094,
    "摸": 3095,
    "手脚": 3096,
    "帮着": 3097,
    "高三": 3098,
    "没错": 3099,
    "虚掩": 3100,
    "女厕所": 3101,
    "闻": 3102,
    "复读": 3103,
    "回潮": 3104,
    "初五": 3105,
    "泡茶": 3106,
    "回南天": 3107,
    "今年过年": 3108,
    "走亲戚": 3109,
    "太累": 3110,
    "·": 3111,
    "一个头": 3112,
    "小姨": 3113,
    "手挽手": 3114,
    "浴室": 3115,
    "不巧": 3116,
    "假期": 3117,
    "女孩子": 3118,
    "忙里忙外": 3119,
    "28": 3120,
    "路由器": 3121,
    "三秒": 3122,
    "滑了一跤": 3123,
    "远远": 3124,
    "陷入": 3125,
    "充电": 3126,
    "值班室": 3127,
    "信鸽": 3128,
    "鸽子": 3129,
    "控制": 3130,
    "急症": 3131,
    "好手": 3132,
    "我到": 3133,
    "家时": 3134,
    "一头": 3135,
    "大龄": 3136,
    "言": 3137,
    "湿滑": 3138,
    "夜班": 3139,
    "兔崽子": 3140,
    "频": 3141,
    "宝马": 3142,
    "皮": 3143,
    "全都": 3144,
    "剩饭": 3145,
    "我开": 3146,
    "不光": 3147,
    "昏迷": 3148,
    "要用": 3149,
    "咂": 3150,
    "瓶子": 3151,
    "理解": 3152,
    "突患": 3153,
    "回国": 3154,
    "精神病院": 3155,
    "阻止": 3156,
    "转移": 3157,
    "九曲": 3158,
    "听不清": 3159,
    "爱替": 3160,
    "哪天": 3161,
    "压得": 3162,
    "千丝": 3163,
    "流水": 3164,
    "老毛病": 3165,
    "班长": 3166,
    "通过": 3167,
    "摆": 3168,
    "抬腿": 3169,
    "正月": 3170,
    "玩具车": 3171,
    "懂得": 3172,
    "他妈": 3173,
    "增长": 3174,
    "自然": 3175,
    "早来": 3176,
    "男方": 3177,
    "都行": 3178,
    "不负": 3179,
    "官": 3180,
    "苦笑": 3181,
    "清洁工": 3182,
    "培养": 3183,
    "什么样": 3184,
    "哈哈": 3185,
    "巴巴": 3186,
    "上次": 3187,
    "众望": 3188,
    "有空": 3189,
    "女娃": 3190,
    "笑够": 3191,
    "早起": 3192,
    "眼里": 3193,
    "疼得": 3194,
    "万人迷": 3195,
    "十六": 3196,
    "求饶": 3197,
    "犯": 3198,
    "硬挺": 3199,
    "雨": 3200,
    "你光": 3201,
    "ベ": 3202,
    "交通事故": 3203,
    "洗衣服": 3204,
    "苦心": 3205,
    "压住": 3206,
    "苦活": 3207,
    "开工": 3208,
    "熟人": 3209,
    "做过": 3210,
    "不至于": 3211,
    "怂恿": 3212,
    "悲伤": 3213,
    "人高马大": 3214,
    "迫不及待": 3215,
    "一打": 3216,
    "香味": 3217,
    "闻到": 3218,
    "影都": 3219,
    "可连个": 3220,
    "义哥": 3221,
    "台风": 3222,
    "楼上": 3223,
    "余钱": 3224,
    "饱嗝儿": 3225,
    "整只": 3226,
    "带回家": 3227,
    "梦想": 3228,
    "采摘": 3229,
    "唾沫星子": 3230,
    "有过": 3231,
    "掐指一算": 3232,
    "膻": 3233,
    "饭后": 3234,
    "别过": 3235,
    "专门": 3236,
    "带出": 3237,
    "年复一年": 3238,
    "千万别": 3239,
    "摸了摸": 3240,
    "噢": 3241,
    "不变": 3242,
    "永远都是": 3243,
    "18": 3244,
    "求助": 3245,
    "至少": 3246,
    "50": 3247,
    "一晃": 3248,
    "中毒": 3249,
    "咽": 3250,
    "过阵": 3251,
    "保利": 3252,
    "泡沫": 3253,
    "先后": 3254,
    "蜡烛": 3255,
    "摞": 3256,
    "玻璃罩": 3257,
    "上放": 3258,
    "摊": 3259,
    "这句": 3260,
    "拐角处": 3261,
    "东街": 3262,
    "信号": 3263,
    "这方面": 3264,
    "赞扬": 3265,
    "每": 3266,
    "夜幕降临": 3267,
    "事业有成": 3268,
    "五个": 3269,
    "下雪": 3270,
    "雪": 3271,
    "部件": 3272,
    "舒服": 3273,
    "转头": 3274,
    "乱飞": 3275,
    "鸡脯": 3276,
    "最贵": 3277,
    "裂缝": 3278,
    "支": 3279,
    "映照": 3280,
    "摆放着": 3281,
    "逼": 3282,
    "盘子": 3283,
    "搪瓷": 3284,
    "保": 3285,
    "利龙": 3286,
    "纸斤": 3287,
    "薅": 3288,
    "鹿犬": 3289,
    "叹息声": 3290,
    "满家": 3291,
    "强迫症": 3292,
    "呼呼大睡": 3293,
    "几": 3294,
    "套房": 3295,
    "独生女": 3296,
    "几栋": 3297,
    "民房": 3298,
    "出租": 3299,
    "难": 3300,
    "原地": 3301,
    "无所谓": 3302,
    "达令": 3303,
    "My": 3304,
    "八": 3305,
    "杀虫剂": 3306,
    "泡水": 3307,
    "见过世面": 3308,
    "泡过": 3309,
    "我边": 3310,
    "往前走": 3311,
    "摆手": 3312,
    "算啦": 3313,
    "不劳": 3314,
    "操心": 3315,
    "600": 3316,
    "脸盆": 3317,
    "盆": 3318,
    "草率": 3319,
    "狗屎": 3320,
    "个步": 3321,
    "倒霉": 3322,
    "第一排": 3323,
    "教过": 3324,
    "不孝有三": 3325,
    "尖叫": 3326,
    "超过": 3327,
    "无后为大": 3328,
    "大三": 3329,
    "牵手": 3330,
    "金砖": 3331,
    "硕大": 3332,
    "舔着": 3333,
    "我身": 3334,
    "笑脸": 3335,
    "这份": 3336,
    "心意": 3337,
    "懂事": 3338,
    "暴露出": 3339,
    "宝": 3340,
    "七夕节": 3341,
    "变回": 3342,
    "辜负": 3343,
    "鞋码": 3344,
    "抬脚": 3345,
    "岂能": 3346,
    "对白": 3347,
    "情人": 3348,
    "偷拍": 3349,
    "码数": 3350,
    "小心": 3351,
    "有力": 3352,
    "相册": 3353,
    "扒拉": 3354,
    "赚": 3355,
    "恩爱": 3356,
    "夫妻": 3357,
    "小三连": 3358,
    "带个": 3359,
    "操场": 3360,
    "一赠": 3361,
    "饱": 3362,
    "赢": 3363,
    "手拉住": 3364,
    "六": 3365,
    "使出": 3366,
    "紧忙": 3367,
    "举手": 3368,
    "乱叫": 3369,
    "汪汪": 3370,
    "踢翻": 3371,
    "饭盆": 3372,
    "跟前": 3373,
    "心爱": 3374,
    "别慌": 3375,
    "我淡定": 3376,
    "六神无主": 3377,
    "五好": 3378,
    "绝招": 3379,
    "三好学生": 3380,
    "即可": 3381,
    "高点": 3382,
    "光棍": 3383,
    "尊严": 3384,
    "美腻": 3385,
    "财": 3386,
    "迎": 3387,
    "老虎": 3388,
    "下铺": 3389,
    "兄弟": 3390,
    "Lgj": 3391,
    "终极": 3392,
    "哪些": 3393,
    "塵緣": 3394,
    "省点": 3395,
    "珠": 3396,
    "双眼": 3397,
    "托着": 3398,
    "思前想后": 3399,
    "袋": 3400,
    "玩完": 3401,
    "太短": 3402,
    "再剪": 3403,
    "看好": 3404,
    "透露": 3405,
    "言语": 3406,
    "喜形于色": 3407,
    "白天黑夜": 3408,
    "巴西": 3409,
    "白辛苦": 3410,
    "就决": 3411,
    "认同": 3412,
    "辛苦": 3413,
    "我话": 3414,
    "由于": 3415,
    "当做": 3416,
    "电费": 3417,
    "超出": 3418,
    "部分": 3419,
    "房租": 3420,
    "福利": 3421,
    "点位": 3422,
    "厚度": 3423,
    "天线": 3424,
    "消炎": 3425,
    "改窜": 3426,
    "稀": 3427,
    "和蔼": 3428,
    "刚出": 3429,
    "复婚": 3430,
    "他会来": 3431,
    "房里": 3432,
    "半夜三更": 3433,
    "如此": 3434,
    "烧上": 3435,
    "热水": 3436,
    "自作多情": 3437,
    "药来": 3438,
    "养生": 3439,
    "翻出": 3440,
    "药箱": 3441,
    "立刻": 3442,
    "38.5": 3443,
    "一试": 3444,
    "安顿": 3445,
    "坚持": 3446,
    "头疼": 3447,
    "哭声": 3448,
    "贴近": 3449,
    "小点": 3450,
    "桶": 3451,
    "坏消息": 3452,
    "很粗": 3453,
    "牙": 3454,
    "针头": 3455,
    "啤酒": 3456,
    "人参": 3457,
    "枸杞": 3458,
    "穷": 3459,
    "我富": 3460,
    "兜里": 3461,
    "不成": 3462,
    "一颗": 3463,
    "幼稚园": 3464,
    "两包": 3465,
    "配个": 3466,
    "鲸鱼": 3467,
    "往回": 3468,
    "百一": 3469,
    "充血": 3470,
    "我量": 3471,
    "嗝": 3472,
    "满身": 3473,
    "新年快乐": 3474,
    "万事如意": 3475,
    "心想事成": 3476,
    "撒泼": 3477,
    "打滚": 3478,
    "撕心裂肺": 3479,
    "凉水澡": 3480,
    "汉堡": 3481,
    "解决不了": 3482,
    "再来一个": 3483,
    "板寸": 3484,
    "蹄子": 3485,
    "捆": 3486,
    "我吸": 3487,
    "凉气": 3488,
    "坐电梯": 3489,
    "洗手": 3490,
    "斤": 3491,
    "147": 3492,
    "不快": 3493,
    "洗头": 3494,
    "坐月子": 3495,
    "脚上": 3496,
    "绳子": 3497,
    "灵活": 3498,
    "理": 3499,
    "哀": 3500,
    "短腿": 3501,
    "郁": 3502,
    "鄙": 3503,
    "嗨": 3504,
    "跳过来": 3505,
    "楼道": 3506,
    "秋风": 3507,
    "豌豆": 3508,
    "骄傲": 3509,
    "无比": 3510,
    "鞋带": 3511,
    "肥": 3512,
    "勉": 3513,
    "有头": 3514,
    "咸淡": 3515,
    "没熟": 3516,
    "三尝": 3517,
    "两尝": 3518,
    "油烟": 3519,
    "做菜": 3520,
    "下厨": 3521,
    "食欲": 3522,
    "你别": 3523,
    "忍俊不禁": 3524,
    "面含": 3525,
    "杀机": 3526,
    "该接": 3527,
    "表里如一": 3528,
    "人要": 3529,
    "教你做": 3530,
    "一心一意": 3531,
    "亲友们": 3532,
    "完毕": 3533,
    "丧事": 3534,
    "时钟": 3535,
    "累死": 3536,
    "指指": 3537,
    "勉强": 3538,
    "梦到": 3539,
    "一跃": 3540,
    "娇小": 3541,
    "卷": 3542,
    "滑拉": 3543,
    "叉腰": 3544,
    "裤": 3545,
    "恨铁不成钢": 3546,
    "晓得": 3547,
    "角": 3548,
    "版四": 3549,
    "童年": 3550,
    "卡哇伊": 3551,
    "露出": 3552,
    "一板": 3553,
    "健胃": 3554,
    "消食片": 3555,
    "两片": 3556,
    "我娇": 3557,
    "裤脚": 3558,
    "空隙": 3559,
    "步调": 3560,
    "寻": 3561,
    "有助于": 3562,
    "消化": 3563,
    "充实": 3564,
    "刚回来": 3565,
    "帽子": 3566,
    "配上": 3567,
    "奶茶": 3568,
    "再加": 3569,
    "退換": 3570,
    "我換": 3571,
    "人回": 3572,
    "粮食": 3573,
    "桌上": 3574,
    "排骨": 3575,
    "脑子": 3576,
    "风卷残云": 3577,
    "动": 3578,
    "筷子": 3579,
    "使眼色": 3580,
    "25": 3581,
    "灰溜溜": 3582,
    "笑话": 3583,
    "来开": 3584,
    "磨": 3585,
    "修好": 3586,
    "鄙视": 3587,
    "玛莎拉蒂": 3588,
    "女士": 3589,
    "废铁": 3590,
    "足够": 3591,
    "话茬": 3592,
    "盒针": 3593,
    "磨针": 3594,
    "刁蛮": 3595,
    "收手": 3596,
    "整天": 3597,
    "糟蹋": 3598,
    "CC": 3599,
    "修": 3600,
    "温暖": 3601,
    "抓痕": 3602,
    "养着": 3603,
    "我亲": 3604,
    "太惯": 3605,
    "拖地": 3606,
    "宅": 3607,
    "枪": 3608,
    "打架": 3609,
    "我招": 3610,
    "撑": 3611,
    "疯婆子": 3612,
    "招惹": 3613,
    "悄悄地": 3614,
    "意外": 3615,
    "比例": 3616,
    "那事": 3617,
    "消停": 3618,
    "聚会": 3619,
    "记号": 3620,
    "几节课": 3621,
    "钱花": 3622,
    "课没上": 3623,
    "越亏": 3624,
    "挽回损失": 3625,
    "二胎": 3626,
    "索然无味": 3627,
    "一切": 3628,
    "说得对": 3629,
    "散步": 3630,
    "拿手菜": 3631,
    "看向": 3632,
    "诗意": 3633,
    "替": 3634,
    "开着车": 3635,
    "传说": 3636,
    "响亮": 3637,
    "清脆": 3638,
    "洋洋自得": 3639,
    "情急之下": 3640,
    "节俭": 3641,
    "孝心": 3642,
    "献": 3643,
    "怪": 3644,
    "脖子": 3645,
    "看不下去": 3646,
    "生了锈": 3647,
    "轴承": 3648,
    "粽": 3649,
    "黏": 3650,
    "温馨": 3651,
    "阳光": 3652,
    "冬日": 3653,
    "赶走": 3654,
    "李焕英": 3655,
    "你好": 3656,
    "电影院": 3657,
    "理直气壮": 3658,
    "混迹江湖": 3659,
    "经验": 3660,
    "房": 3661,
    "两女": 3662,
    "嗐": 3663,
    "一点点": 3664,
    "退下来": 3665,
    "费劲": 3666,
    "找准": 3667,
    "上画": 3668,
    "拿笔": 3669,
    "熟练工": 3670,
    "打针": 3671,
    "不良": 3672,
    "休闲服": 3673,
    "顺其自然": 3674,
    "自卑": 3675,
    "保险": 3676,
    "法宝": 3677,
    "靓丽": 3678,
    "呔": 3679,
    "时尚": 3680,
    "英俊潇洒": 3681,
    "藏门": 3682,
    "金斗": 3683,
    "混元": 3684,
    "阵": 3685,
    "黄河": 3686,
    "玉树临风": 3687,
    "格格不入": 3688,
    "半侣": 3689,
    "画": 3690,
    "提上": 3691,
    "就行了": 3692,
    "柔软": 3693,
    "好听": 3694,
    "听听": 3695,
    "艳遇": 3696,
    "要不得": 3697,
    "飞来横祸": 3698,
    "高冷": 3699,
    "婉拒": 3700,
    "不屑一顾": 3701,
    "引来": 3702,
    "不算": 3703,
    "太高": 3704,
    "刮目相看": 3705,
    "掰": 3706,
    "世俗": 3707,
    "当年": 3708,
    "10": 3709,
    "回床": 3710,
    "顺眼": 3711,
    "恋爱": 3712,
    "自由": 3713,
    "点到": 3714,
    "人配": 3715,
    "几十人": 3716,
    "再见": 3717,
    "三十": 3718,
    "焕发": 3719,
    "大漠": 3720,
    "照发": 3721,
    "这特": 3722,
    "小群": 3723,
    "大街": 3724,
    "泡妞": 3725,
    "活": 3726,
    "腻歪": 3727,
    "一头雾水": 3728,
    "紧接着": 3729,
    "合": 3730,
    "乳牙": 3731,
    "多久": 3732,
    "出没": 3733,
    "痴心妄想": 3734,
    "春": 3735,
    "刚长": 3736,
    "两边": 3737,
    "捏": 3738,
    "回道": 3739,
    "多大": 3740,
    "爸道": 3741,
    "人口普查": 3742,
    "人口": 3743,
    "还少": 3744,
    "好些个": 3745,
    "洗换": 3746,
    "用品": 3747,
    "举动": 3748,
    "逗笑": 3749,
    "猜": 3750,
    "微笑": 3751,
    "馋": 3752,
    "满口答应": 3753,
    "提了": 3754,
    "小男孩": 3755,
    "拜拜": 3756,
    "赶忙": 3757,
    "顺着": 3758,
    "路线": 3759,
    "脸色": 3760,
    "咱妈": 3761,
    "男盆友": 3762,
    "恍然大悟": 3763,
    "随后": 3764,
    "摸不着头脑": 3765,
    "奇葩": 3766,
    "不让": 3767,
    "偏僻": 3768,
    "我关": 3769,
    "门外": 3770,
    "疑惑": 3771,
    "摸摸": 3772,
    "眉毛": 3773,
    "邹着": 3774,
    "一摊": 3775,
    "伍牛柒": 3776,
    "婶": 3777,
    "变回来": 3778,
    "沙如雪": 3779,
    "带你去": 3780,
    "人来领": 3781,
    "怒目": 3782,
    "来领": 3783,
    "赶快": 3784,
    "没领": 3785,
    "公婆": 3786,
    "小路": 3787,
    "乡间": 3788,
    "乌七八糟": 3789,
    "翻过来": 3790,
    "封面": 3791,
    "拐进": 3792,
    "一本": 3793,
    "鸡笼": 3794,
    "编程": 3795,
    "欣喜": 3796,
    "没好气": 3797,
    "互损": 3798,
    "冤家": 3799,
    "钩": 3800,
    "如": 3801,
    "远山": 3802,
    "汇报": 3803,
    "战果": 3804,
    "完菜": 3805,
    "五块": 3806,
    "叨咕": 3807,
    "总有": 3808,
    "驴": 3809,
    "💩": 3810,
    "夏": 3811,
    "冬": 3812,
    "他叔": 3813,
    "家当": 3814,
    "快乐": 3815,
    "寒假": 3816,
    "宝贝": 3817,
    "笼子": 3818,
    "市场": 3819,
    "大清早": 3820,
    "放寒假": 3821,
    "诀窍": 3822,
    "他进": 3823,
    "上楼": 3824,
    "夹": 3825,
    "盯住": 3826,
    "爷们": 3827,
    "如法炮制": 3828,
    "贴着": 3829,
    "刘哥": 3830,
    "这厮": 3831,
    "赵凑": 3832,
    "主": 3833,
    "热乎": 3834,
    "赶不上": 3835,
    "喊出": 3836,
    "孽": 3837,
    "起劲": 3838,
    "过不去": 3839,
    "光膀子": 3840,
    "三点钟": 3841,
    "画面": 3842,
    "难忘": 3843,
    "流汗": 3844,
    "掉色": 3845,
    "满头": 3846,
    "汗水": 3847,
    "从头": 3848,
    "后排": 3849,
    "撇": 3850,
    "徐徐": 3851,
    "金榜题名": 3852,
    "洞房花烛": 3853,
    "他乡遇故知": 3854,
    "空调": 3855,
    "喷完": 3856,
    "颜色": 3857,
    "得意洋洋": 3858,
    "煮茶": 3859,
    "大半": 3860,
    "路由": 3861,
    "电源": 3862,
    "拔": 3863,
    "亲爹": 3864,
    "亲娘": 3865,
    "DsRabbit": 3866,
    "可比": 3867,
    "敲门": 3868,
    "容易": 3869,
    "永远": 3870,
    "不醒": 3871,
    "装睡": 3872,
    "左脚": 3873,
    "球友": 3874,
    "意见": 3875,
    "族群": 3876,
    "比卖": 3877,
    "花儿": 3878,
    "谢": 3879,
    "接电话": 3880,
    "接收": 3881,
    "出家": 3882,
    "血族": 3883,
    "比较满意": 3884,
    "小赖子": 3885,
    "大笑": 3886,
    "电视节目": 3887,
    "一下子": 3888,
    "四五个": 3889,
    "人围": 3890,
    "一把汗": 3891,
    "选出": 3892,
    "麻麻": 3893,
    "光辉": 3894,
    "矮个子": 3895,
    "胖随": 3896,
    "力气": 3897,
    "男同学": 3898,
    "打哭": 3899,
    "为娘": 3900,
    "事迹": 3901,
    "好几遍": 3902,
    "孤酒": 3903,
    "老人": 3904,
    "关心": 3905,
    "我操": 3906,
    "挑剔": 3907,
    "反反复复": 3908,
    "正版": 3909,
    "对门": 3910,
    "订婚": 3911,
    "没来": 3912,
    "径直": 3913,
    "走来": 3914,
    "认出": 3915,
    "同志": 3916,
    "允许": 3917,
    "摆摊儿": 3918,
    "磕头": 3919,
    "所迫": 3920,
    "掏": 3921,
    "驴子": 3922,
    "做不了": 3923,
    "主了": 3924,
    "没辙": 3925,
    "4": 3926,
    "竟": 3927,
    "世态炎凉": 3928,
    "拦不住": 3929,
    "叶落": 3930,
    "蒸时": 3931,
    "葱姜": 3932,
    "红烧肉": 3933,
    "祖上": 3934,
    "宫里": 3935,
    "御厨": 3936,
    "紫枫": 3937,
    "炎": 3938,
    "开卡": 3939,
    "开卡宴": 3940,
    "换悍": 3941,
    "马才行": 3942,
    "凭": 3943,
    "世态": 3944,
    "好了没": 3945,
    "邻": 3946,
    "说太熟": 3947,
    "长袖": 3948,
    "扯下来": 3949,
    "不料": 3950,
    "布": 3951,
    "倒忙": 3952,
    "闪过": 3953,
    "片段": 3954,
    "袖子": 3955,
    "但事": 3956,
    "结时": 3957,
    "清楚": 3958,
    "还手": 3959,
    "且": 3960,
    "嫁给": 3961,
    "拒绝": 3962,
    "从权": 3963,
    "男女授受不亲": 3964,
    "礼盒": 3965,
    "曼妙": 3966,
    "一大早": 3967,
    "严禁": 3968,
    "调戏": 3969,
    "违者": 3970,
    "凹凸": 3971,
    "致": 3972,
    "玲珑": 3973,
    "虽说": 3974,
    "起身": 3975,
    "塑料": 3976,
    "裂": 3977,
    "带肉": 3978,
    "夹住": 3979,
    "直喊": 3980,
    "看病": 3981,
    "既然": 3982,
    "口流": 3983,
    "情景": 3984,
    "姨姐": 3985,
    "家俩": 3986,
    "手持": 3987,
    "探测器": 3988,
    "强力": 3989,
    "吸铁石": 3990,
    "手疾眼快": 3991,
    "抓起": 3992,
    "塞进": 3993,
    "吐": 3994,
    "炫耀着": 3995,
    "好运气": 3996,
    "探测": 3997,
    "各自": 3998,
    "相互指责": 3999,
    "比如说": 4000,
    "之内": 4001,
    "范围": 4002,
    "女婿": 4003,
    "坚冰": 4004,
    "好细": 4005,
    "细致": 4006,
    "今": 4007,
    "点心": 4008,
    "写错": 4009,
    "造反": 4010,
    "往年": 4011,
    "敢揍": 4012,
    "生个": 4013,
    "不拉": 4014,
    "预计": 4015,
    "别回": 4016,
    "钱数": 4017,
    "端": 4018,
    "评评理": 4019,
    "放下": 4020,
    "讲桌": 4021,
    "鬼": 4022,
    "赖": 4023,
    "赖到": 4024,
    "大名": 4025,
    "第一天": 4026,
    "斑竹": 4027,
    "砰砰": 4028,
    "第一眼": 4029,
    "响": 4030,
    "遵守": 4031,
    "虎": 4032,
    "盘": 4033,
    "白带": 4034,
    "从头到尾": 4035,
    "活是": 4036,
    "结衣": 4037,
    "淡淡地": 4038,
    "全校": 4039,
    "这盘": 4040,
    "肯教": 4041,
    "避": 4042,
    "瘟神": 4043,
    "上届": 4044,
    "这届": 4045,
    "踢皮球": 4046,
    "岛国": 4047,
    "模式": 4048,
    "转到": 4049,
    "初一": 4050,
    "黑眼镜": 4051,
    "魔鬼身材": 4052,
    "职业装": 4053,
    "扫过来": 4054,
    "两声": 4055,
    "咳嗽": 4056,
    "．": 4057,
    "七八点": 4058,
    "三顿": 4059,
    "饭桶": 4060,
    "败家子": 4061,
    "坚定不移": 4062,
    "猫叔": 4063,
    "突发": 4064,
    "一白": 4065,
    "常": 4066,
    "俯卧撑": 4067,
    "灌满": 4068,
    "水当": 4069,
    "健身器材": 4070,
    "练练": 4071,
    "白天": 4072,
    "一鞭": 4073,
    "坏处": 4074,
    "矮": 4075,
    "面值": 4076,
    "冥币": 4077,
    "还给": 4078,
    "摇": 4079,
    "李辉": 4080,
    "平平": 4081,
    "舅妈": 4082,
    "果不其然": 4083,
    "呵斥": 4084,
    "解释一下": 4085,
    "十里": 4086,
    "柔情": 4087,
    "一帘": 4088,
    "幽梦": 4089,
    "未雨绸缪": 4090,
    "伐": 4091,
    "锁": 4092,
    "帅": 4093,
    "提到": 4094,
    "抱到": 4095,
    "沿": 4096,
    "厅里": 4097,
    "如此这般": 4098,
    "挺好玩": 4099,
    "意犹未尽": 4100,
    "蹲": 4101,
    "练": 4102,
    "挺美": 4103,
    "腰象": 4104,
    "挨": 4105,
    "旺": 4106,
    "财疼": 4107,
    "几组": 4108,
    "深": 4109,
    "鸡动": 4110,
    "发绿": 4111,
    "装满水": 4112,
    "讲究": 4113,
    "地往": 4114,
    "孔里": 4115,
    "杀菌": 4116,
    "防水": 4117,
    "再用": 4118,
    "肩": 4119,
    "保鲜袋": 4120,
    "折卷": 4121,
    "孔": 4122,
    "严实": 4123,
    "完美": 4124,
    "挽": 4125,
    "火候": 4126,
    "葱花": 4127,
    "花椒油": 4128,
    "料酒": 4129,
    "约个": 4130,
    "委婉": 4131,
    "隐藏": 4132,
    "着想": 4133,
    "痛定思痛": 4134,
    "更好": 4135,
    "俏丽": 4136,
    "马": 4137,
    "爹爹": 4138,
    "同样": 4139,
    "速度": 4140,
    "相互": 4141,
    "擦肩而过": 4142,
    "教他": 4143,
    "苦口婆心": 4144,
    "婉约": 4145,
    "成人": 4146,
    "密密麻麻": 4147,
    "一招": 4148,
    "出山": 4149,
    "这条": 4150,
    "最靓": 4151,
    "崽": 4152,
    "全体": 4153,
    "试探性": 4154,
    "凭借": 4155,
    "男同事": 4156,
    "剑": 4157,
    "地板": 4158,
    "兰花": 4159,
    "一霸": 4160,
    "爆炸": 4161,
    "额": 4162,
    "咋办": 4163,
    "慢慢来": 4164,
    "不叠": 4165,
    "五六十": 4166,
    "仰起": 4167,
    "往上": 4168,
    "五楼": 4169,
    "一男一女": 4170,
    "互扯": 4171,
    "扔下来": 4172,
    "友善": 4173,
    "齐": 4174,
    "散伙": 4175,
    "交流": 4176,
    "憋着": 4177,
    "推推": 4178,
    "没戏": 4179,
    "滚": 4180,
    "运气": 4181,
    "不一会": 4182,
    "数落": 4183,
    "三哈": 4184,
    "足足": 4185,
    "还罚": 4186,
    "再有": 4187,
    "下次": 4188,
    "养成": 4189,
    "学会": 4190,
    "两哈": 4191,
    "耶": 4192,
    "扔下去": 4193,
    "流浪汉": 4194,
    "窗台": 4195,
    "墙脚": 4196,
    "过夜": 4197,
    "正冷得": 4198,
    "整体": 4199,
    "报名": 4200,
    "一百": 4201,
    "经历": 4202,
    "JOJO": 4203,
    "问声": 4204,
    "猛一看": 4205,
    "挂满": 4206,
    "关爱": 4207,
    "弱智": 4208,
    "死亡": 4209,
    "退群": 4210,
    "凹下": 4211,
    "凸": 4212,
    "难不成": 4213,
    "善举": 4214,
    "摆脱": 4215,
    "活该": 4216,
    "做人": 4217,
    "纷纷": 4218,
    "二舅": 4219,
    "言论": 4220,
    "事儿": 4221,
    "哈哈哈": 4222,
    "银行": 4223,
    "雪人": 4224,
    "对大号": 4225,
    "发表": 4226,
    "进行": 4227,
    "刺激": 4228,
    "肉麻": 4229,
    "阿谀奉承": 4230,
    "正为": 4231,
    "高招": 4232,
    "感到": 4233,
    "沾沾自喜": 4234,
    "玩手": 4235,
    "等待": 4236,
    "比赛": 4237,
    "游戏": 4238,
    "苛刻": 4239,
    "勾搭": 4240,
    "沉迷": 4241,
    "带进": 4242,
    "操控": 4243,
    "类": 4244,
    "流星": 4245,
    "根烟": 4246,
    "蝴蝶剑": 4247,
    "武器": 4248,
    "望远镜": 4249,
    "对手": 4250,
    "孤单": 4251,
    "华南区": 4252,
    "老实巴交": 4253,
    "目瞪口呆": 4254,
    "多人": 4255,
    "苯": 4256,
    "撇嘴": 4257,
    "不理": 4258,
    "大步": 4259,
    "推子": 4260,
    "推": 4261,
    "荳": 4262,
    "小豆": 4263,
    "车边": 4264,
    "学大": 4265,
    "大佬": 4266,
    "自带": 4267,
    "BGM": 4268,
    "出场": 4269,
    "肆意": 4270,
    "那货": 4271,
    "款式": 4272,
    "做工": 4273,
    "行云流水": 4274,
    "人太多": 4275,
    "某": 4276,
    "音号": 4277,
    "魁梧": 4278,
    "短发": 4279,
    "八卦掌": 4280,
    "虎虎生威": 4281,
    "长得帅": 4282,
    "关公": 4283,
    "舞": 4284,
    "杀气": 4285,
    "十足": 4286,
    "小腿": 4287,
    "得不到": 4288,
    "挡不住": 4289,
    "丫头": 4290,
    "毁": 4291,
    "60": 4292,
    "醉酒": 4293,
    "舞剑": 4294,
    "砍": 4295,
    "..": 4296,
    "笨手": 4297,
    "笨手笨脚": 4298,
    "多岁": 4299,
    "不满": 4300,
    "眼角": 4301,
    "染色": 4302,
    "毛巾": 4303,
    "只好": 4304,
    "几分": 4305,
    "偏向": 4306,
    "宁愿": 4307,
    "呆若木鸡": 4308,
    "娇滴滴": 4309,
    "白莲": 4310,
    "钟声": 4311,
    "心灵": 4312,
    "全部": 4313,
    "鱼歌": 4314,
    "浅": 4315,
    "唱": 4316,
    "卖力气": 4317,
    "一瞬间": 4318,
    "泥": 4319,
    "后背": 4320,
    "祖传秘方": 4321,
    "生抽": 4322,
    "老抽": 4323,
    "蚝油": 4324,
    "灵隐寺": 4325,
    "滴": 4326,
    "除非": 4327,
    "两栋": 4328,
    "比武": 4329,
    "打赢": 4330,
    "绝不": 4331,
    "纠缠": 4332,
    "离母": 4333,
    "隔": 4334,
    "老鼠": 4335,
    "浓郁": 4336,
    "挎着": 4337,
    "一个包": 4338,
    "微风": 4339,
    "迎面": 4340,
    "清香": 4341,
    "香醇": 4342,
    "小猫咪": 4343,
    "轮流": 4344,
    "布料": 4345,
    "治一治": 4346,
    "命苦": 4347,
    "别哭": 4348,
    "男左女右": 4349,
    "堵死": 4350,
    "怨": 4351,
    "怨声载道": 4352,
    "坏毛病": 4353,
    "胆小": 4354,
    "急得": 4355,
    "真急": 4356,
    "大叫": 4357,
    "来不及": 4358,
    "匆忙": 4359,
    "打印纸": 4360,
    "亲爸": 4361,
    "怕老婆": 4362,
    "新表": 4363,
    "外国人": 4364,
    "花色": 4365,
    "质地": 4366,
    "一清二楚": 4367,
    "哪一年": 4368,
    "唐装": 4369,
    "流行起来": 4370,
    "悟出": 4371,
    "控": 4372,
    "通用": 4373,
    "临走时": 4374,
    "我拉到": 4375,
    "悄悄": 4376,
    "纸尿裤": 4377,
    "这点": 4378,
    "调查表": 4379,
    "表": 4380,
    "烟是": 4381,
    "拍照": 4382,
    "80s": 4383,
    "放着": 4384,
    "没人开": 4385,
    "拿来": 4386,
    "使用": 4387,
    "灰": 4388,
    "诉苦": 4389,
    "彩色": 4390,
    "车车": 4391,
    "受苦": 4392,
    "几乎": 4393,
    "这下": 4394,
    "人车": 4395,
    "团聚": 4396,
    "记": 4397,
    "带到": 4398,
    "富裕": 4399,
    "装修": 4400,
    "符合": 4401,
    "动手动脚": 4402,
    "电子": 4403,
    "电子厂": 4404,
    "服装厂": 4405,
    "明年": 4406,
    "举止": 4407,
    "书生": 4408,
    "极其": 4409,
    "相似": 4410,
    "嫑": 4411,
    "拍错": 4412,
    "马屁": 4413,
    "爬格子": 4414,
    "手撑": 4415,
    "哈喇子": 4416,
    "妈来": 4417,
    "村": 4418,
    "白光": 4419,
    "耀眼": 4420,
    "麻": 4421,
    "烧灼感": 4422,
    "吹胡子瞪眼": 4423,
    "几两": 4424,
    "烧酒": 4425,
    "胆正": 4426,
    "好多年": 4427,
    "我闭": 4428,
    "简直": 4429,
    "娇羞": 4430,
    "什是": 4431,
    "天上": 4432,
    "天庭": 4433,
    "电焊": 4434,
    "质问": 4435,
    "客观存在": 4436,
    "丧心病狂": 4437,
    "我道": 4438,
    "小妮子": 4439,
    "快点": 4440,
    "热茶": 4441,
    "交": 4442,
    "顶不住": 4443,
    "背锅": 4444,
    "反驳": 4445,
    "观点": 4446,
    "截然": 4447,
    "相反": 4448,
    "引用": 4449,
    "中外": 4450,
    "专家": 4451,
    "踏破": 4452,
    "女娲": 4453,
    "补天": 4454,
    "停下来": 4455,
    "跑过来": 4456,
    "包工头": 4457,
    "外地人": 4458,
    "蒲扇": 4459,
    "摆摆手": 4460,
    "那家伙": 4461,
    "尘土飞扬": 4462,
    "尘土": 4463,
    "绝尘而去": 4464,
    "牌子": 4465,
    "没见": 4466,
    "还来": 4467,
    "大树": 4468,
    "冲着": 4469,
    "滚滚": 4470,
    "马路上": 4471,
    "气温": 4472,
    "睁眼": 4473,
    "上升": 4474,
    "仙女下凡": 4475,
    "滋味": 4476,
    "闭": 4477,
    "着眼": 4478,
    "祸": 4479,
    "闭着": 4480,
    "乘凉": 4481,
    "尿急": 4482,
    "离": 4483,
    "越近": 4484,
    "行百里者半九十": 4485,
    "中央": 4486,
    "树底下": 4487,
    "训斥": 4488,
    "娱乐节目": 4489,
    "电都": 4490,
    "儿郎": 4491,
    "十几张": 4492,
    "学期": 4493,
    "好几张": 4494,
    "最不缺": 4495,
    "胡说": 4496,
    "分析": 4497,
    "国家": 4498,
    "霸气": 4499,
    "给我发": 4500,
    "证": 4501,
    "受": 4502,
    "法律": 4503,
    "交给": 4504,
    "Zona": 4505,
    "没事儿": 4506,
    "作业本": 4507,
    "纸老虎": 4508,
    "齐恩娅": 4509,
    "儿童乐园": 4510,
    "以示": 4511,
    "厕": 4512,
    "光着": 4513,
    "股在": 4514,
    "处理": 4515,
    "哀怨": 4516,
    "废书作": 4517,
    "兽性": 4518,
    "按住": 4519,
    "恶狠狠": 4520,
    "降智": 4521,
    "咸饼": 4522,
    "分": 4523,
    "娜娜": 4524,
    "求生欲": 4525,
    "哪像": 4526,
    "不见": 4527,
    "你哥": 4528,
    "过期": 4529,
    "减肥茶": 4530,
    "乖乖": 4531,
    "拿走": 4532,
    "云": 4533,
    "回信": 4534,
    "瞄": 4535,
    "轴": 4536,
    "连续": 4537,
    "可怜": 4538,
    "振动模式": 4539,
    "一宿": 4540,
    "走过": 4541,
    "别误会": 4542,
    "妥妥": 4543,
    "久违": 4544,
    "吊": 4545,
    "<": 4546,
    "#": 4547,
    "≦": 4548,
    "电源板": 4549,
    "爸电": 4550,
    "弹": 4551,
    "树上": 4552,
    "粘住": 4553,
    "老骂": 4554,
    "烦死": 4555,
    "修鞋": 4556,
    "睡午觉": 4557,
    "滴到": 4558,
    "嘴皮": 4559,
    "小兄弟": 4560,
    "怎样": 4561,
    "女老师": 4562,
    "四五岁": 4563,
    "试没试": 4564,
    "盆子": 4565,
    "反复": 4566,
    "冲洗": 4567,
    "会变": 4568,
    "一颗颗": 4569,
    "异常": 4570,
    "光亮": 4571,
    "变小": 4572,
    "我越": 4573,
    "洗越": 4574,
    "害怕": 4575,
    "有毒": 4576,
    "恐惧": 4577,
    "勇敢": 4578,
    "丰满": 4579,
    "双职工": 4580,
    "做些": 4581,
    "干不出": 4582,
    "妈养": 4583,
    "往后": 4584,
    "吃食": 4585,
    "揪住": 4586,
    "神经病": 4587,
    "全家": 4588,
    "原本": 4589,
    "必要": 4590,
    "就算": 4591,
    "看了又看": 4592,
    "显": 4593,
    "锅盖": 4594,
    "嗡嗡响": 4595,
    "干点活": 4596,
    "爱意": 4597,
    "放弃": 4598,
    "宁可": 4599,
    "规规矩矩": 4600,
    "纳尼": 4601,
    "六月": 4602,
    "飞雪": 4603,
    "直至": 4604,
    "声嘶力竭": 4605,
    "地喊": 4606,
    "地站": 4607,
    "满脑袋": 4608,
    "受伤": 4609,
    "紫药水": 4610,
    "凑近": 4611,
    "咬牙切齿": 4612,
    "打成": 4613,
    "整整": 4614,
    "问号": 4615,
    "迷茫": 4616,
    "药死": 4617,
    "可见": 4618,
    "总揍": 4619,
    "卡其色": 4620,
    "娉娉婷婷": 4621,
    "超美": 4622,
    "一成": 4623,
    "清秀": 4624,
    "娉婷": 4625,
    "白花花": 4626,
    "一分钟": 4627,
    "二楼": 4628,
    "晾晒": 4629,
    "屋子里": 4630,
    "闭上": 4631,
    "末日": 4632,
    "胡须": 4633,
    "图书": 4634,
    "少儿": 4635,
    "鬼祟": 4636,
    "危险品": 4637,
    "不易": 4638,
    "触": 4639,
    "碰到": 4640,
    "可不": 4641,
    "瞎": 4642,
    "好奇心": 4643,
    "人们": 4644,
    "顿起": 4645,
    "椅子": 4646,
    "高高的": 4647,
    "门框": 4648,
    "利用": 4649,
    "一捆": 4650,
    "默契": 4651,
    "天怒人怨": 4652,
    "圆圆的": 4653,
    "蓝": 4654,
    "炕": 4655,
    "老实": 4656,
    "罐子": 4657,
    "撅": 4658,
    "腚": 4659,
    "秋裤": 4660,
    "刷遍": 4661,
    "一阵子": 4662,
    "角角落落": 4663,
    "水缸": 4664,
    "洗不掉": 4665,
    "刮胡刀": 4666,
    "监工": 4667,
    "刮破": 4668,
    "屋": 4669,
    "灰色": 4670,
    "一回": 4671,
    "生命": 4672,
    "他养": 4673,
    "仰面": 4674,
    "罪魁祸首": 4675,
    "换成": 4676,
    "离家出走": 4677,
    "思想": 4678,
    "它们": 4679,
    "芳香": 4680,
    "实验": 4681,
    "总之": 4682,
    "吃软不吃硬": 4683,
    "涕泪": 4684,
    "横流": 4685,
    "祸害": 4686,
    "重话": 4687,
    "略带": 4688,
    "小饼": 4689,
    "放松": 4690,
    "家家": 4691,
    "欢庆": 4692,
    "家守": 4693,
    "老鼠药": 4694,
    "罪": 4695,
    "乱七八糟": 4696,
    "戒备": 4697,
    "尝试": 4698,
    "我妈举": 4699,
    "尽管": 4700,
    "你爷": 4701,
    "你奶": 4702,
    "呆呆地": 4703,
    "吓人": 4704,
    "己经": 4705,
    "股后": 4706,
    "输钱": 4707,
    "净": 4708,
    "爆": 4709,
    "挨着": 4710,
    "全是": 4711,
    "伙伴": 4712,
    "批发": 4713,
    "地摊货": 4714,
    "至于": 4715,
    "非说": 4716,
    "不足以": 4717,
    "表达": 4718,
    "歉意": 4719,
    "两件": 4720,
    "三件": 4721,
    "五件": 4722,
    "后妈": 4723,
    "阻拦": 4724,
    "请来": 4725,
    "强行": 4726,
    "花雨": 4727,
    "到位": 4728,
    "部位": 4729,
    "下方": 4730,
    "过处": 4731,
    "水花四溅": 4732,
    "漫天": 4733,
    "一幕": 4734,
    "处分": 4735,
    "光彩": 4736,
    "声尖叫": 4737,
    "鸡飞狗跳": 4738,
    "气味": 4739,
    "熏天": 4740,
    "欲哭无泪": 4741,
    "饭菜": 4742,
    "正常": 4743,
    "碟子": 4744,
    "我姐": 4745,
    "小女生": 4746,
    "KFC": 4747,
    "住户": 4748,
    "有长": 4749,
    "鲅鱼圈": 4750,
    "姐长": 4751,
    "哗然": 4752,
    "大爷": 4753,
    "没多大": 4754,
    "成熟": 4755,
    "功能": 4756,
    "以外": 4757,
    "麻烦": 4758,
    "丢人": 4759,
    "一百多块": 4760,
    "辫子": 4761,
    "刚洗": 4762,
    "借": 4763,
    "几轮": 4764,
    "报道": 4765,
    "人事": 4766,
    "惊艳": 4767,
    "一部分": 4768,
    "同仁": 4769,
    "认领": 4770,
    "收长": 4771,
    "沈阳": 4772,
    "年轻人": 4773,
    "连声": 4774,
    "谢都": 4775,
    "拿给": 4776,
    "楼底下": 4777,
    "一抓": 4778,
    "准": 4779,
    "抢过": 4780,
    "杏眼": 4781,
    "命运": 4782,
    "可才": 4783,
    "开映": 4784,
    "几分钟": 4785,
    "严重": 4786,
    "报告": 4787,
    "借口": 4788,
    "桌声": 4789,
    "开溜": 4790,
    "我张": 4791,
    "长个": 4792,
    "尿意": 4793,
    "来袭": 4794,
    "越涨": 4795,
    "所有人": 4796,
    "敲": 4797,
    "偶尔": 4798,
    "凌空": 4799,
    "讲台": 4800,
    "挥斥": 4801,
    "方遒": 4802,
    "美极了": 4803,
    "悲剧": 4804,
    "打瞌睡": 4805,
    "飞来": 4806,
    "到场": 4807,
    "正中": 4808,
    "脑门": 4809,
    "肿起": 4810,
    "老大": 4811,
    "今天下午": 4812,
    "教育局": 4813,
    "试图": 4814,
    "撇向": 4815,
    "迅雷不及掩耳之势": 4816,
    "这一": 4817,
    "装满": 4818,
    "液体": 4819,
    "往面": 4820,
    "其他人": 4821,
    "打掩护": 4822,
    "逃过": 4823,
    "触电": 4824,
    "点赞时": 4825,
    "推给": 4826,
    "眼疾手快": 4827,
    "盖": 4828,
    "按上": 4829,
    "另一只": 4830,
    "手以": 4831,
    "余热": 4832,
    "机智": 4833,
    "把玩": 4834,
    "很快": 4835,
    "此刻": 4836,
    "颗": 4837,
    "炸弹": 4838,
    "随时": 4839,
    "引爆": 4840,
    "圈里": 4841,
    "饼干": 4842,
    "正当": 4843,
    "落": 4844,
    "吩咐": 4845,
    "我点": 4846,
    "矮下": 4847,
    "水龙头": 4848,
    "快完了": 4849,
    "同去": 4850,
    "多余": 4851,
    "旅馆": 4852,
    "最帅": 4853,
    "小气": 4854,
    "囧": 4855,
    "途": 4856,
    "北堂": 4857,
    "灵梦": 4858,
    "小哥": 4859,
    "坏小孩": 4860,
    "800": 4861,
    "cium": 4862,
    "慢镜": 4863,
    "慢镜头": 4864,
    "妩": 4865,
    "媚": 4866,
    "性": 4867,
    "哎呀呀": 4868,
    "电线杆": 4869,
    "试试": 4870,
    "两科": 4871,
    "不太好": 4872,
    "重视": 4873,
    "一视同仁": 4874,
    "妥当": 4875,
    "我压": 4876,
    "着火": 4877,
    "省事": 4878,
    "麻蛋": 4879,
    "打不开": 4880,
    "一毛": 4881,
    "及时": 4882,
    "宽": 4883,
    "异样": 4884,
    "回头一看": 4885,
    "感": 4886,
    "憋气": 4887,
    "定地": 4888,
    "莫": 4889,
    "巴拉巴": 4890,
    "不怪": 4891,
    "只怪": 4892,
    "副": 4893,
    "嘴脸": 4894,
    "我特": 4895,
    "看清楚": 4896,
    "开支": 4897,
    "火车票": 4898,
    "售票点": 4899,
    "电影票": 4900,
    "算不算": 4901,
    "老人家": 4902,
    "愿望": 4903,
    "培训": 4904,
    "买菜": 4905,
    "把头": 4906,
    "挣扎": 4907,
    "钻出来": 4908,
    "长发": 4909,
    "全糊上": 4910,
    "呛水": 4911,
    "霹雳": 4912,
    "扑隆": 4913,
    "溺死": 4914,
    "钓竿": 4915,
    "用处": 4916,
    "行情": 4917,
    "投": 4918,
    "积少成多": 4919,
    "大用": 4920,
    "年底": 4921,
    "这么晚": 4922,
    "很淡": 4923,
    "韭菜": 4924,
    "几排": 4925,
    "孩": 4926,
    "长途车": 4927,
    "歪": 4928,
    "呼呼": 4929,
    "极致": 4930,
    "丢脸": 4931,
    "打不醒": 4932,
    "嘎": 4933,
    "质疑": 4934,
    "亲妈": 4935,
    "苹果": 4936,
    "卧铺": 4937,
    "四仰八叉": 4938,
    "爸傲": 4939,
    "小黑": 4940,
    "呆笨": 4941,
    "车厢": 4942,
    "仨": 4943,
    "萝卜": 4944,
    "大头菜": 4945,
    "粉条": 4946,
    "特点": 4947,
    "作证": 4948,
    "转悠": 4949,
    "大包": 4950,
    "持续": 4951,
    "小裹": 4952,
    "凯旋": 4953,
    "归": 4954,
    "好几": 4955,
    "锅": 4956,
    "撑死": 4957,
    "娇地": 4958,
    "使": 4959,
    "关耳来": 4960,
    "当着": 4961,
    "两条": 4962,
    "后腿": 4963,
    "弯": 4964,
    "前爪": 4965,
    "上爬": 4966,
    "这猫": 4967,
    "上蹿下跳": 4968,
    "垂死挣扎": 4969,
    "瘸": 4970,
    "吊死": 4971,
    "没等我": 4972,
    "上来": 4973,
    "耳光": 4974,
    "三脚": 4975,
    "蒙": 4976,
    "拖鞋": 4977,
    "别的": 4978,
    "开学": 4979,
    "旅客": 4980,
    "急眼": 4981,
    "那人": 4982,
    "呢子": 4983,
    "裙子": 4984,
    "大二": 4985,
    "搬": 4986,
    "礼拜天": 4987,
    "四楼": 4988,
    "老二": 4989,
    "矫健": 4990,
    "翻过": 4991,
    "语": 4992,
    "重心": 4993,
    "铁锤": 4994,
    "王": 4995,
    "老病号": 4996,
    "幸福": 4997,
    "听得": 4998,
    "暖暖的": 4999,
    "贴身": 5000,
    "棉袄": 5001,
    "白疼": 5002,
    "越高": 5003,
    "抽抽噎噎": 5004,
    "总觉": 5005,
    "一顺": 5006,
    "迷": 5007,
    "专柜": 5008,
    "37": 5009,
    "左顺鞋": 5010,
    "卖不出去": 5011,
    "调換": 5012,
    "大哭": 5013,
    "换钱": 5014,
    "咱家": 5015,
    "仅仅": 5016,
    "拍板": 5017,
    "宣布": 5018,
    "录取": 5019,
    "颜值": 5020,
    "唯有": 5021,
    "报答": 5022,
    "明星": 5023,
    "装不下": 5024,
    "待在家里": 5025,
    "造": 5026,
    "素质": 5027,
    "上个星期": 5028,
    "两车": 5029,
    "果子": 5030,
    "从那之后": 5031,
    "坚决": 5032,
    "没脸": 5033,
    "尝一尝": 5034,
    "别老是": 5035,
    "丫丫": 5036,
    "买个": 5037,
    "品尝": 5038,
    "收费": 5039,
    "\"": 5040,
    "说明": 5041,
    "成年人": 5042,
    "酒精": 5043,
    "饮品": 5044,
    "笑靥": 5045,
    "如花": 5046,
    "代驾": 5047,
    "很漂亮": 5048,
    "接下来": 5049,
    "老听": 5050,
    "确": 5051,
    "摇摇头": 5052,
    "畜": 5053,
    "靠着": 5054,
    "树撒": 5055,
    "就果": 5056,
    "却说": 5057,
    "没看": 5058,
    "刚一": 5059,
    "忘记": 5060,
    "红烧": 5061,
    "端过来": 5062,
    "干掉": 5063,
    "结": 5064,
    "二十五块": 5065,
    "这学": 5066,
    "亲自": 5067,
    "阶段": 5068,
    "过关斩将": 5069,
    "品不": 5070,
    "平静": 5071,
    "胸怀": 5072,
    "倘若": 5073,
    "这湖": 5074,
    "宽阔": 5075,
    "即使": 5076,
    "从此以后": 5077,
    "领悟到": 5078,
    "唠唠叨叨": 5079,
    "狸": 5080,
    "土豆": 5081,
    "脸肿": 5082,
    "别用": 5083,
    "偷用": 5084,
    "湖面": 5085,
    "一脸茫然": 5086,
    "疼不疼": 5087,
    "蹲下": 5088,
    "不用谢": 5089,
    "去取": 5090,
    "蹦蹦": 5091,
    "拿过": 5092,
    "时问": 5093,
    "蒙得": 5094,
    "用餐": 5095,
    "湖水": 5096,
    "愉快": 5097,
    "本村": 5098,
    "首席": 5099,
    "电工": 5100,
    "前方": 5101,
    "湖说": 5102,
    "肿成": 5103,
    "痒": 5104,
    "十分激烈": 5105,
    "惊慌": 5106,
    "兴奋不已": 5107,
    "第二碗": 5108,
    "青如": 5109,
    "碧玉": 5110,
    "滑落": 5111,
    "锅里": 5112,
    "大学毕业": 5113,
    "即化": 5114,
    "当地": 5115,
    "有名气": 5116,
    "人长": 5117,
    "几十个": 5118,
    "应聘者": 5119,
    "竞争": 5120,
    "赞不绝口": 5121,
    "老同学": 5122,
    "不痒": 5123,
    "o": 5124,
    "暗自": 5125,
    "再坏": 5126,
    "掐": 5127,
    "高大": 5128,
    "效果": 5129,
    "拿命": 5130,
    "ZWX": 5131,
    "十几个": 5132,
    "兜风": 5133,
    "涂": 5134,
    "口红": 5135,
    "飞快": 5136,
    "三轮车": 5137,
    "拉着": 5138,
    "主要": 5139,
    "模样": 5140,
    "搭话": 5141,
    "不忍心": 5142,
    "惨": 5143,
    "几人": 5144,
    "合计": 5145,
    "掀开": 5146,
    "大半夜": 5147,
    "骂街": 5148,
    "畅快": 5149,
    "此事": 5150,
    "不了了之": 5151,
    "照常上课": 5152,
    "背地里": 5153,
    "整": 5154,
    "轻多": 5155,
    "面带笑容": 5156,
    "教鞭": 5157,
    "要告": 5158,
    "妈关": 5159,
    "趴在": 5160,
    "叹气": 5161,
    "咚": 5162,
    "渠道": 5163,
    "远处": 5164,
    "哭笑不得": 5165,
    "落汤鸡": 5166,
    "我直": 5167,
    "撒谎": 5168,
    "中邪": 5169,
    "能管": 5170,
    "可怕": 5171,
    "照样": 5172,
    "塞满": 5173,
    "放狗": 5174,
    "那狗": 5175,
    "耳刮子": 5176,
    "罚站": 5177,
    "轻言细语": 5178,
    "自顾自": 5179,
    "时五": 5180,
    "岸上": 5181,
    "滚上来": 5182,
    "识趣": 5183,
    "膨胀": 5184,
    "压根": 5185,
    "深水": 5186,
    "水里互": 5187,
    "区游": 5188,
    "土坷垃": 5189,
    "抱起": 5190,
    "河里": 5191,
    "抓人": 5192,
    "前脚": 5193,
    "稀泥": 5194,
    "进水": 5195,
    "犯错": 5196,
    "旷课": 5197,
    "告状": 5198,
    "极尽": 5199,
    "听话": 5200,
    "余": 5201,
    "越加": 5202,
    "偷鸡摸狗": 5203,
    "早退": 5204,
    "扑": 5205,
    "开课": 5206,
    "严厉": 5207,
    "禁止": 5208,
    "水库": 5209,
    "表面": 5210,
    "实则": 5211,
    "跳过去": 5212,
    "姨": 5213,
    "不相为": 5214,
    "窝里": 5215,
    "接待": 5216,
    "不仅": 5217,
    "特会": 5218,
    "又续": 5219,
    "聪明": 5220,
    "蛋生": 5221,
    "鸟会": 5222,
    "返工": 5223,
    "不乖": 5224,
    "也许": 5225,
    "巴掌": 5226,
    "哇": 5227,
    "紧张": 5228,
    ".......": 5229,
    "完卡": 5230,
    "凉": 5231,
    "慢着": 5232,
    "修成": 5233,
    "打击": 5234,
    "就加": 5235,
    "微信": 5236,
    "整一下": 5237,
    "伸出手": 5238,
    "祝福": 5239,
    "正果": 5240,
    "烧红": 5241,
    "真想": 5242,
    "韩家": 5243,
    "庄": 5244,
    "小伙": 5245,
    "极好": 5246,
    "铁匠铺": 5247,
    "没吐": 5248,
    "星星点点": 5249,
    "不同": 5250,
    "认命": 5251,
    "恨": 5252,
    "背上": 5253,
    "睡着": 5254,
    "事成": 5255,
    "定局": 5256,
    "无力回天": 5257,
    "从来不": 5258,
    "招够": 5259,
    "假如": 5260,
    "绕道": 5261,
    "水渠": 5262,
    "狭路相逢": 5263,
    "无可": 5264,
    "另一边": 5265,
    "小两口": 5266,
    "时塞俩": 5267,
    "发给": 5268,
    "悠着点": 5269,
    "熬": 5270,
    "痘痘": 5271,
    "池塘": 5272,
    "洗脚": 5273,
    "惊为天人": 5274,
    "苦日子": 5275,
    "一旦": 5276,
    "亲嘴": 5277,
    "这门": 5278,
    "亲事": 5279,
    "闹洞房": 5280,
    "浮漂": 5281,
    "同心": 5282,
    "坨": 5283,
    "白白的": 5284,
    "姓白": 5285,
    "阳台门": 5286,
    "面壁思过": 5287,
    "婆娘": 5288,
    "炒个": 5289,
    "难得": 5290,
    "过次": 5291,
    "二人": 5292,
    "二两": 5293,
    "远去": 5294,
    "憋屈": 5295,
    "嚎啕大哭": 5296,
    "这一哭": 5297,
    "有毒气体": 5298,
    "吸进": 5299,
    "吐出来": 5300,
    "堪比": 5301,
    "满清": 5302,
    "别急": 5303,
    "停止": 5304,
    "开锁": 5305,
    "闻着": 5306,
    "投降": 5307,
    "踢踢": 5308,
    "踏踏": 5309,
    "那气": 5310,
    "循环": 5311,
    "我缩": 5312,
    "味儿": 5313,
    "屁臭": 5314,
    "理会": 5315,
    "不多时": 5316,
    "问贼": 5317,
    "娃子": 5318,
    "抽死": 5319,
    "开门": 5320,
    "十大": 5321,
    "酷刑": 5322,
    "深呼吸": 5323,
    "大快朵颐": 5324,
    "恋": 5325,
    "前任": 5326,
    "问价": 5327,
    "306": 5328,
    "咬咬牙": 5329,
    "正等待": 5330,
    "梦醒": 5331,
    "暴怒": 5332,
    "接触": 5333,
    "欣慰": 5334,
    "没付": 5335,
    "到家": 5336,
    "科": 5337,
    "科学": 5338,
    "冲过来": 5339,
    "如同": 5340,
    "后门": 5341,
    "劳资": 5342,
    "不停": 5343,
    "两眼": 5344,
    "口吐白沫": 5345,
    "抽搐": 5346,
    "偶然": 5347,
    "特么": 5348,
    "徒弟": 5349,
    "板砖": 5350,
    "尽心尽力": 5351,
    "教": 5352,
    "我妹": 5353,
    "完后": 5354,
    "解气": 5355,
    "很乖": 5356,
    "辣": 5357,
    "不堪": 5358,
    "污浊": 5359,
    "灵光": 5360,
    "气笑": 5361,
    "一跤": 5362,
    "一溜烟": 5363,
    "河边": 5364,
    "挺过": 5365,
    "这关": 5366,
    "一现": 5367,
    "媳妇儿": 5368,
    "当即": 5369,
    "不出所料": 5370,
    "鬼鬼祟祟": 5371,
    "躲进": 5372,
    "大衣柜": 5373,
    "完气": 5374,
    "扔下": 5375,
    "未来": 5376,
    "有效": 5377,
    "编谎": 5378,
    "抄起": 5379,
    "出门时": 5380,
    "东面": 5381,
    "脸往": 5382,
    "方向": 5383,
    "更欢": 5384,
    "家狗": 5385,
    "不妙": 5386,
    "下崽帮": 5387,
    "水沟": 5388,
    "老奶奶": 5389,
    "炸牛": 5390,
    "打开门": 5391,
    "慈祥": 5392,
    "此时此刻": 5393,
    "骂骂咧咧": 5394,
    "空气": 5395,
    "钉": 5396,
    "门上": 5397,
    "吸": 5398,
    "两口": 5399,
    "新鲜空气": 5400,
    "整晕": 5401,
    "主意": 5402,
    "锁扣": 5403,
    "两秒": 5404,
    "石": 5405,
    "老幺": 5406,
    "滚回来": 5407,
    "逮到": 5408,
    "过程": 5409,
    "无声无息": 5410,
    "移开": 5411,
    "动抬眼": 5412,
    "真能": 5413,
    "熏": 5414,
    "捂": 5415,
    "偷笑": 5416,
    "说响": 5417,
    "不响": 5418,
    "这屁": 5419,
    "润物细无声": 5420,
    "绿": 5421,
    "生闷气": 5422,
    "会儿": 5423,
    "把门": 5424,
    "开条": 5425,
    "呼吸": 5426,
    "正坐": 5427,
    "床边": 5428,
    "搭理": 5429,
    "柜子": 5430,
    "取酒": 5431,
    "纹丝": 5432,
    "缘分": 5433,
    "不渡": 5434,
    "肚": 5435,
    "子火": 5436,
    "牛粪": 5437,
    "炮竹": 5438,
    "我大吼": 5439,
    "搁": 5440,
    "闪开": 5441,
    "我来": 5442,
    "助跑": 5443,
    "飞脚": 5444,
    "哭天抹泪": 5445,
    "鬼哭狼嚎": 5446,
    "没出息": 5447,
    "蛋炒饭": 5448,
    "梆硬": 5449,
    "那信": 5450,
    "深思熟虑": 5451,
    "毅然决然": 5452,
    "嫁人": 5453,
    "2021": 5454,
    "世界末日": 5455,
    "自我": 5456,
    "毒蛇": 5457,
    "一斤": 5458,
    "环绕": 5459,
    "蛇": 5460,
    "烦恼": 5461,
    "解决": 5462,
    "tm": 5463,
    "八块": 5464,
    "冻": 5465,
    "到头": 5466,
    "做点": 5467,
    "红光满面": 5468,
    "反感": 5469,
    "某音": 5470,
    "改编": 5471,
    "天堂": 5472,
    "张望": 5473,
    "餐巾纸": 5474,
    "废": 5475,
    "市里": 5476,
    "旋风腿": 5477,
    "足球": 5478,
    "射门": 5479,
    "见不得人": 5480,
    "不出": 5481,
    "我料": 5482,
    "AAB": 5483,
    "能往": 5484,
    "拜小登": 5485,
    "现金": 5486,
    "喊道": 5487,
    "病": 5488,
    "拼命": 5489,
    "淡定": 5490,
    "包里": 5491,
    "一千五百元": 5492,
    "治病": 5493,
    "流下": 5494,
    "张卡": 5495,
    "停下": 5496,
    "困难": 5497,
    "冲动": 5498,
    "保持良好": 5499,
    "心态": 5500,
    "一无是处": 5501,
    "颓废": 5502,
    "没过几天": 5503,
    "待理不理": 5504,
    "醉": 5505,
    "红颜": 5506,
    "倒闭": 5507,
    "改卖": 5508,
    "李太高": 5509,
    "本身": 5510,
    "恼火": 5511,
    "红尘": 5512,
    "李道": 5513,
    "咨询": 5514,
    "拉家常": 5515,
    "唠": 5516,
    "高姿态": 5517,
    "不鸟": 5518,
    "一笑": 5519,
    "同名": 5520,
    "错误": 5521,
    "口气": 5522,
    "疯传": 5523,
    "妊娠": 5524,
    "没脸见人": 5525,
    "农村": 5526,
    "安胎": 5527,
    "叹": 5528,
    "动物园": 5529,
    "牌位": 5530,
    "打猎": 5531,
    "园子": 5532,
    "祭祖": 5533,
    "赫然": 5534,
    "祠堂": 5535,
    "供奉": 5536,
    "能招": 5537,
    "承认错误": 5538,
    "不景气": 5539,
    "撩": 5540,
    "大闺女": 5541,
    "汤勺": 5542,
    "一勺": 5543,
    "不脏": 5544,
    "亲弟": 5545,
    "我脏": 5546,
    "降温": 5547,
    "过分": 5548,
    "陈给": 5549,
    "加热管": 5550,
    "冻死": 5551,
    "图纸": 5552,
    "海鲜": 5553,
    "越来": 5554,
    "黄": 5555,
    "喂喂": 5556,
    "保证": 5557,
    "清一色": 5558,
    "行动": 5559,
    "不成想": 5560,
    "辞职报告": 5561,
    "投入": 5562,
    "除": 5563,
    "之外": 5564,
    "三十多岁": 5565,
    "抗议": 5566,
    "老爷": 5567,
    "照顾": 5568,
    "逗弄": 5569,
    "晕": 5570,
    "段子": 5571,
    "离谱": 5572,
    "一走": 5573,
    "后脚": 5574,
    "吃素": 5575,
    "外边": 5576,
    "养颜": 5577,
    "药材": 5578,
    "猪宝": 5579,
    "薛": 5580,
    "伸舌头": 5581,
    "示范": 5582,
    "派": 5583,
    "探": 5584,
    "探口风": 5585,
    "将要": 5586,
    "多个": 5587,
    "四周": 5588,
    "凝重": 5589,
    "凑": 5590,
    "耳边": 5591,
    "排毒": 5592,
    "送过来": 5593,
    "兴高采烈": 5594,
    "我下": 5595,
    "送点": 5596,
    "珠宝": 5597,
    "人心": 5598,
    "合适": 5599,
    "需求": 5600,
    "唯唯诺诺": 5601,
    "盒子": 5602,
    "问闺蜜": 5603,
    "毛茸": 5604,
    "尖刺": 5605,
    "圆形": 5606,
    "奇特": 5607,
    "物体": 5608,
    "不禁": 5609,
    "日": 5610,
    "很酸爽": 5611,
    "一两根": 5612,
    "十几米": 5613,
    "他用": 5614,
    "招来": 5615,
    "三四岁": 5616,
    "一抖": 5617,
    "啪": 5618,
    "滚出": 5619,
    "远才": 5620,
    "诚意": 5621,
    "止住": 5622,
    "好事": 5623,
    "忙不迭": 5624,
    "云淡风轻": 5625,
    "高人": 5626,
    "做派": 5627,
    "不信": 5628,
    "法不轻传": 5629,
    "心法": 5630,
    "思想斗争": 5631,
    "传男不传": 5632,
    "骨骼": 5633,
    "精奇": 5634,
    "练武": 5635,
    "奇才": 5636,
    "翻来覆去": 5637,
    "好多天": 5638,
    "口水": 5639,
    "做出": 5640,
    "违背": 5641,
    "祖宗": 5642,
    "近十年": 5643,
    "手中": 5644,
    "吞": 5645,
    "趁热打铁": 5646,
    "好感": 5647,
    "小说": 5648,
    "衡水": 5649,
    "相当": 5650,
    "滋润": 5651,
    "号码": 5652,
    "下落": 5653,
    "得知": 5654,
    "消息": 5655,
    "寒腿": 5656,
    "儿女": 5657,
    "干不了": 5658,
    "忍痛": 5659,
    "此": 5660,
    "招商": 5661,
    "衡": 5662,
    "价格": 5663,
    "相夫教子": 5664,
    "他生": 5665,
    "还价": 5666,
    "翘首": 5667,
    "厚厚的": 5668,
    "羽绒服": 5669,
    "开着": 5670,
    "防滑": 5671,
    "机票": 5672,
    "飞到": 5673,
    "期盼": 5674,
    "精英": 5675,
    "苦苦": 5676,
    "紧紧": 5677,
    "泣不成声": 5678,
    "继承": 5679,
    "叱咤": 5680,
    "商界": 5681,
    "一万": 5682,
    "如想": 5683,
    "节奏": 5684,
    "不语": 5685,
    "改天": 5686,
    "不宜": 5687,
    "一个劲": 5688,
    "内向": 5689,
    "食不言": 5690,
    "寝": 5691,
    "没教": 5692,
    "游戏卡": 5693,
    "刚挂": 5694,
    "不去": 5695,
    "车倒": 5696,
    "夸夸": 5697,
    "喜笑颜开": 5698,
    "可真帅": 5699,
    "别过来": 5700,
    "流量": 5701,
    "扩大": 5702,
    "自福": 5703,
    "南极": 5704,
    "赤道": 5705,
    "一并": 5706,
    "总价": 5707,
    "一万五": 5708,
    "卫星": 5709,
    "保上": 5710,
    "占": 5711,
    "衣锦夜行": 5712,
    "小王子": 5713,
    "不怕死": 5714,
    "半死不活": 5715,
    "怕疼": 5716,
    "带瓶": 5717,
    "房门口": 5718,
    "以免": 5719,
    "走火入魔": 5720,
    "两双": 5721,
    "先生": 5722,
    "XX": 5723,
    "早恋": 5724,
    "搂搂抱抱": 5725,
    "不像话": 5726,
    "凶神恶煞": 5727,
    "发慌": 5728,
    "中华": 5729,
    "先开": 5730,
    "口说": 5731,
    "学了": 5732,
    "添油": 5733,
    "加醋": 5734,
    "....": 5735,
    "算算": 5736,
    "软": 5737,
    "闪到": 5738,
    "刘肉": 5739,
    "一喊": 5740,
    "整栋": 5741,
    "颤抖": 5742,
    "差一点": 5743,
    "地震": 5744,
    "结结巴巴": 5745,
    "段": 5746,
    "一包": 5747,
    "沐浴露": 5748,
    "冷死": 5749,
    "没脱": 5750,
    "好又多": 5751,
    "58": 5752,
    "舒肤佳": 5753,
    "黑影": 5754,
    "叮": 5755,
    "赔钱": 5756,
    "电子锁": 5757,
    "家属": 5758,
    "暂时": 5759,
    "送到": 5760,
    "治疗": 5761,
    "开展": 5762,
    "一步": 5763,
    "按钮": 5764,
    "证件": 5765,
    "比较忙": 5766,
    "20": 5767,
    "多分钟": 5768,
    "拍门": 5769,
    "哪个": 5770,
    "一指": 5771,
    "联系": 5772,
    "语无伦次": 5773,
    "哐啷": 5774,
    "干哈": 5775,
    "劈头盖脸": 5776,
    "捶": 5777,
    "汉语": 5778,
    "博大精深": 5779,
    "谨言慎行": 5780,
    "川上": 5781,
    "知": 5782,
    "精神病人": 5783,
    "摔跤": 5784,
    "现如今": 5785,
    "明白": 5786,
    "单纯": 5787,
    "追不上": 5788,
    "怎么回事": 5789,
    "呕": 5790,
    "歪歪": 5791,
    "双掌": 5792,
    "最怕": 5793,
    "按照": 5794,
    "五六个": 5795,
    "人收": 5796,
    "五毛钱": 5797,
    "绝世武功": 5798,
    "进展": 5799,
    "正传": 5800,
    "退钱": 5801,
    "尤": 5802,
    "外婆": 5803,
    "两棵树": 5804,
    "补过": 5805,
    "文化": 5806,
    "福": 5807,
    "绝无": 5808,
    "这人": 5809,
    "离职": 5810,
    "轻重": 5811,
    "贴": 5812,
    "背后": 5813,
    "十": 5814,
    "武林中": 5815,
    "讲武": 5816,
    "徳": 5817,
    "不可": 5818,
    "上当": 5819,
    "轻易": 5820,
    "飘然": 5821,
    "牢牢": 5822,
    "记住": 5823,
    "捏碎": 5824,
    "小云": 5825,
    "利": 5826,
    "一个月": 5827,
    "叽叽": 5828,
    "坏蛋": 5829,
    "多前": 5830,
    "石头": 5831,
    "开水": 5832,
    "一口气": 5833,
    "喝光": 5834,
    "反尔淡定": 5835,
    "个色": 5836,
    "事得": 5837,
    "腰带": 5838,
    "幸亏": 5839,
    "撞见": 5840,
    "骑个": 5841,
    "电动车": 5842,
    "撞": 5843,
    "二十年": 5844,
    "白开水": 5845,
    "认真": 5846,
    "里边儿": 5847,
    "天花乱坠": 5848,
    "入": 5849,
    "坑": 5850,
    "国军": 5851,
    "太太": 5852,
    "送个": 5853,
    "借条": 5854,
    "女儿红": 5855,
    "借款人": 5856,
    "借款": 5857,
    "黑天": 5858,
    "顶上": 5859,
    "嫁妆": 5860,
    "同龄": 5861,
    "裹": 5862,
    "西装": 5863,
    "光屁股": 5864,
    "崭新": 5865,
    "连包": 5866,
    "两宿": 5867,
    "杠杠": 5868,
    "录用": 5869,
    "设计院": 5870,
    "熬夜": 5871,
    "用纸": 5872,
    "梁山伯": 5873,
    "祝英": 5874,
    "抬杠": 5875,
    "问门": 5876,
    "核试验": 5877,
    "夯": 5878,
    "昆": 5879,
    "勥": 5880,
    "包几宿": 5881,
    "蹦": 5882,
    "泰迪": 5883,
    "缝上": 5884,
    "胖香": 5885,
    "留疤": 5886,
    "瘦": 5887,
    "圆鼓鼓": 5888,
    "气球": 5889,
    "洞": 5890,
    "皱巴成": 5891,
    "品种": 5892,
    "啥样": 5893,
    "遛狗": 5894,
    "不栓绳": 5895,
    "jg": 5896,
    "这狗": 5897,
    "挺护主": 5898,
    "茓": 5899,
    "菿": 5900,
    "奣": 5901,
    "高档": 5902,
    "始终": 5903,
    "穷小子": 5904,
    "战战兢兢": 5905,
    "企业家": 5906,
    "难堪": 5907,
    "大酒店": 5908,
    "席间": 5909,
    "情意": 5910,
    "娇生惯养": 5911,
    "彩礼": 5912,
    "人民币": 5913,
    "这番话": 5914,
    "无异": 5915,
    "炸雷": 5916,
    "奈何": 5917,
    "纵使": 5918,
    "方式": 5919,
    "味道": 5920,
    "粉蒸肉": 5921,
    "可不可以": 5922,
    "讨论": 5923,
    "诸葛": 5924,
    "思慧": 5925,
    "我表": 5926,
    "忘不掉": 5927,
    "房产": 5928,
    "山鹰": 5929,
    "寂寞": 5930,
    "个富": 5931,
    "上市": 5932,
    "公司老总": 5933,
    "多处": 5934,
    "上去": 5935,
    "妇女节": 5936,
    "更快": 5937,
    "魂飞魄散": 5938,
    "睁开眼睛": 5939,
    "搂": 5940,
    "笑嘻嘻": 5941,
    "亲亲": 5942,
    "血盆大口": 5943,
    "凑来": 5944,
    "全倒": 5945,
    "冰": 5946,
    "冲出": 5947,
    "对视": 5948,
    "一秒": 5949,
    "最先": 5950,
    "报仇": 5951,
    "吼声": 5952,
    "弄醒": 5953,
    "往五叔": 5954,
    "逃跑": 5955,
    "翻进": 5956,
    "浮现": 5957,
    "锅子": 5958,
    "掀": 5959,
    "求求": 5960,
    "不当": 5961,
    "轻车熟路": 5962,
    "睡大觉": 5963,
    "批改作业": 5964,
    "震天响": 5965,
    "邪恶": 5966,
    "床头": 5967,
    "闪": 5968,
    "成就感": 5969,
    "折回去": 5970,
    "握草": 5971,
    "趁五": 5972,
    "驾驶室": 5973,
    "潇洒": 5974,
    "依旧": 5975,
    "认真听讲": 5976,
    "戒尺": 5977,
    "上呼": 5978,
    "冷声": 5979,
    "青龙": 5980,
    "刺向": 5981,
    "拦下": 5982,
    "他人": 5983,
    "布加迪": 5984,
    "威龙": 5985,
    "2.2": 5986,
    "肥硕": 5987,
    "钻进": 5988,
    "画风": 5989,
    "翔": 5990,
    "愣神": 5991,
    "妆容": 5992,
    "夺路": 5993,
    "大门": 5994,
    "抓条": 5995,
    "扁担": 5996,
    "顶": 5997,
    "红彤彤": 5998,
    "全到": 5999,
    "打出": 6000,
    "醒目": 6001,
    "关二哥": 6002,
    "红": 6003,
    "猛": 6004,
    "痕迹": 6005,
    "本该": 6006,
    "人均": 6007,
    "月工资": 6008,
    "不足": 6009,
    "现已": 6010,
    "恶劣": 6011,
    "造就": 6012,
    "个个": 6013,
    "超群": 6014,
    "酒量": 6015,
    "商机": 6016,
    "身无分文": 6017,
    "爱斯基摩": 6018,
    "看出": 6019,
    "心思": 6020,
    "举杯": 6021,
    "代理费": 6022,
    "铺": 6023,
    "货": 6024,
    "寒冷": 6025,
    "十万": 6026,
    "前程": 6027,
    "无声": 6028,
    "赞": 6029,
    "好酒": 6030,
    "做生意": 6031,
    "双目": 6032,
    "片片": 6033,
    "雪花": 6034,
    "飘落": 6035,
    "北极圈": 6036,
    "愿不愿意": 6037,
    "总代理": 6038,
    "抿": 6039,
    "天寒地冻": 6040,
    "方便": 6041,
    "默然": 6042,
    "信心": 6043,
    "光明": 6044,
    "回味": 6045,
    "K": 6046,
    "极限": 6047,
    "酒商": 6048,
    "卖到": 6049,
    "脱销": 6050,
    "当地人": 6051,
    "御寒": 6052,
    "歌": 6053,
    "冷到": 6054,
    "蹦迪": 6055,
    "送礼": 6056,
    "两年": 6057,
    "积累": 6058,
    "惊人": 6059,
    "财富": 6060,
    "人类": 6061,
    "浑身是劲": 6062,
    "走投无路": 6063,
    "排起": 6064,
    "店面": 6065,
    "了衡": 6066,
    "代理": 6067,
    "骗": 6068,
    "火到": 6069,
    "门前": 6070,
    "蜿蜒": 6071,
    "喝了酒": 6072,
    "长队": 6073,
    "更令": 6074,
    "雪橇": 6075,
    "百公里": 6076,
    "油耗": 6077,
    "二斤": 6078,
    "悠长": 6079,
    "绵纯": 6080,
    "两千": 6081,
    "一场场": 6082,
    "求职": 6083,
    "心上人": 6084,
    "受尽": 6085,
    "屈辱": 6086,
    "励精图治": 6087,
    "出头之日": 6088,
    "磨难": 6089,
    "国": 6090,
    "经验不足": 6091,
    "频频": 6092,
    "辞退": 6093,
    "贸易": 6094,
    "致使": 6095,
    "损失": 6096,
    "各大": 6097,
    "一无所有": 6098,
    "酒醉": 6099,
    "猛抽": 6100,
    "年代": 6101,
    "无异于": 6102,
    "天文数字": 6103,
    "一支": 6104,
    "劣质": 6105,
    "香烟": 6106,
    "几口": 6107,
    "那晚": 6108,
    "心如刀割": 6109,
    "句": 6110,
    "不配": 6111,
    "日语": 6112,
    "没志气": 6113,
    "瞎了眼": 6114,
    "亿": 6115,
    "蝴蝶": 6116,
    "香甜": 6117,
    "桌前": 6118,
    "寄": 6119,
    "抱头痛哭": 6120,
    "不已": 6121,
    "了此残生": 6122,
    "小胡子": 6123,
    "一举一动": 6124,
    "一饮而尽": 6125,
    "酩酊大醉": 6126,
    "这酒": 6127,
    "细品": 6128,
    "品": 6129,
    "醇香": 6130,
    "浓烈": 6131,
    "上头": 6132,
    "遗书": 6133,
    "无望": 6134,
    "三十六": 6135,
    "顺水": 6136,
    "楼一跃": 6137,
    "失业": 6138,
    "无人问津": 6139,
    "合伙": 6140,
    "小本": 6141,
    "顺风": 6142,
    "著名": 6143,
    "八年": 6144,
    "变故": 6145,
    "商人": 6146,
    "货品": 6147,
    "血本无归": 6148,
    "期限": 6149,
    "已过": 6150,
    "梦若": 6151
}